{"version":3,"kind":"Article","sha256":"11d04a5ee53561c2ce4bd029d999fbe6261f11544a20baab29e63c1ce1fa3989","slug":"lectures.data-sharing.data-sharing","location":"/lectures/3.3_data_sharing/3.3_data_sharing.md","dependencies":[],"frontmatter":{"title":"3.3 Data Sharing","content_includes_title":false,"github":"https://github.com/EO-college/cubes-and-clouds","subject":"Cubes and Clouds learning materials","numbering":{"title":{"offset":2}},"source_url":"https://github.com/EO-college/cubes-and-clouds/blob/main/lectures/3.3_data_sharing/3.3_data_sharing.md","edit_url":"https://github.com/EO-college/cubes-and-clouds/edit/main/lectures/3.3_data_sharing/3.3_data_sharing.md","thumbnail":"/cubes-and-clouds/build/4066423c8fb88d808f30ad74224294b4.jpeg","exports":[{"format":"md","filename":"3.3_data_sharing.md","url":"/cubes-and-clouds/build/3.3_data_sharing-d44e10de997a8751d4577e0c90013d9e.md"}]},"mdast":{"type":"root","children":[{"type":"block","children":[{"type":"heading","depth":2,"position":{"start":{"line":3,"column":1},"end":{"line":3,"column":1}},"children":[{"type":"text","value":"Learning Objectives","position":{"start":{"line":3,"column":1},"end":{"line":3,"column":1}},"key":"OCDTH7feSt"}],"identifier":"learning-objectives","label":"Learning Objectives","html_id":"learning-objectives","implicit":true,"key":"GVnbaZykhN"},{"type":"list","ordered":false,"spread":false,"position":{"start":{"line":4,"column":1},"end":{"line":7,"column":1}},"children":[{"type":"listItem","spread":true,"position":{"start":{"line":4,"column":1},"end":{"line":4,"column":1}},"children":[{"type":"paragraph","children":[{"type":"text","value":"Carry out an EO workflow on a cloud platform independently","position":{"start":{"line":4,"column":1},"end":{"line":4,"column":1}},"key":"pvsVM4qPA9"}],"key":"EIsYF7602y"}],"key":"L4q3s8M4hR"},{"type":"listItem","spread":true,"position":{"start":{"line":5,"column":1},"end":{"line":5,"column":1}},"children":[{"type":"paragraph","children":[{"type":"text","value":"Make our results ","position":{"start":{"line":5,"column":1},"end":{"line":5,"column":1}},"key":"oXAieAv0O8"},{"type":"inlineCode","value":"open","position":{"start":{"line":5,"column":1},"end":{"line":5,"column":1}},"key":"BUSVwbcnBj"},{"type":"text","value":" and ","position":{"start":{"line":5,"column":1},"end":{"line":5,"column":1}},"key":"R5jOCQA83X"},{"type":"inlineCode","value":"FAIR","position":{"start":{"line":5,"column":1},"end":{"line":5,"column":1}},"key":"HWFbEB0nAU"}],"key":"PepgHRgPBR"}],"key":"TfkDyzSSUn"},{"type":"listItem","spread":true,"position":{"start":{"line":6,"column":1},"end":{"line":7,"column":1}},"children":[{"type":"paragraph","children":[{"type":"text","value":"Collaborate with a community of researchers to reach a common goal","position":{"start":{"line":6,"column":1},"end":{"line":6,"column":1}},"key":"a7T680bFht"}],"key":"SjwajgBzlD"}],"key":"ol2CFg6SE6"}],"key":"eoRNUf9qzx"},{"type":"heading","depth":2,"position":{"start":{"line":8,"column":1},"end":{"line":8,"column":1}},"children":[{"type":"text","value":"Introduction","position":{"start":{"line":8,"column":1},"end":{"line":8,"column":1}},"key":"wiiyA2ARPS"}],"identifier":"introduction","label":"Introduction","html_id":"introduction","implicit":true,"key":"gX8Xk4ZxiS"},{"type":"paragraph","position":{"start":{"line":9,"column":1},"end":{"line":10,"column":1}},"children":[{"type":"text","value":"We have reached the last chapter of the course. You know about data cubes, cloud platforms and open science. Now it’s time to prove it! We will apply everything we have learned so far and complete our own EO workflow on a cloud platform adhering to the open science principles.\nWe have carried out a full EO workflow to produce snow cover information in an alpine catchment. To make our results impactful we need to make them openly available to other researchers and the general public. Therefore we are going to learn how to share our data set (and code) properly - following the FAIR principles. We have learned about the concepts of open science in lecture ","position":{"start":{"line":9,"column":1},"end":{"line":9,"column":1}},"key":"kU2m3koYAb"},{"type":"link","url":"https://github.com/EO-College/cubes-and-clouds/blob/main/lectures/1.3_openscience/1.3.1_openscienceandfair.md","position":{"start":{"line":9,"column":1},"end":{"line":9,"column":1}},"children":[{"type":"text","value":"1.3 open science","position":{"start":{"line":9,"column":1},"end":{"line":9,"column":1}},"key":"EAcCrvzYXG"}],"urlSource":"https://github.com/EO-College/cubes-and-clouds/blob/main/lectures/1.3_openscience/1.3.1_openscienceandfair.md","data":{"kind":"file","org":"EO-College","repo":"cubes-and-clouds","reference":"main","file":"lectures/1.3_openscience/1.3.1_openscienceandfair.md","raw":"https://raw.githubusercontent.com/EO-College/cubes-and-clouds/main/lectures/1.3_openscience/1.3.1_openscienceandfair.md"},"internal":false,"protocol":"github","key":"vjNFnLvyZQ"},{"type":"text","value":". Now we are going to apply them! We are going to create a snow cover area map of the alps together with all the participants of the course. Everyone adds their contribution to a shared map. With every participant another small patch of the alps gets mapped! The map is openly available so that everybody can track our progress, the data is openly available and you can point to the patch you have provided!","position":{"start":{"line":9,"column":1},"end":{"line":9,"column":1}},"key":"gFrCbEXLye"}],"key":"J1uYT9BqTh"},{"type":"paragraph","position":{"start":{"line":12,"column":1},"end":{"line":12,"column":1}},"children":[{"type":"link","url":"https://www.youtube.com/watch?v=-8rHmtEMCx8","position":{"start":{"line":12,"column":1},"end":{"line":12,"column":1}},"children":[{"type":"image","url":"/cubes-and-clouds/build/4066423c8fb88d808f30ad74224294b4.jpeg","alt":"Your Open Science Journey","position":{"start":{"line":12,"column":1},"end":{"line":12,"column":1}},"key":"mWl3KAjIKI","urlSource":"https://img.youtube.com/vi/-8rHmtEMCx8/0.jpg"}],"urlSource":"https://www.youtube.com/watch?v=-8rHmtEMCx8","key":"IVBhljREN1"},{"type":"text","value":" ","position":{"start":{"line":12,"column":1},"end":{"line":12,"column":1}},"key":"fBDnFj8nmM"},{"type":"break","key":"awDPIg4BaI"}],"key":"NxFFHXZnPk"},{"type":"blockquote","position":{"start":{"line":13,"column":1},"end":{"line":18,"column":1}},"children":[{"type":"paragraph","position":{"start":{"line":13,"column":1},"end":{"line":15,"column":1}},"children":[{"type":"text","value":"Video content in cooperation with ","position":{"start":{"line":13,"column":1},"end":{"line":13,"column":1}},"key":"s784c2NYpA"},{"type":"link","url":"https://opengeohub.org/people/leandro-parente/","position":{"start":{"line":13,"column":1},"end":{"line":13,"column":1}},"children":[{"type":"text","value":"Leandro Parente","position":{"start":{"line":13,"column":1},"end":{"line":13,"column":1}},"key":"mxKtO8L3au"}],"urlSource":"https://opengeohub.org/people/leandro-parente/","key":"VVVMchkgyJ"},{"type":"text","value":" (OpenGeoHub). ","position":{"start":{"line":13,"column":1},"end":{"line":13,"column":1}},"key":"SF27JL7wAf"},{"type":"break","key":"CDYdVCtnNr"},{"type":"text","value":"\n","position":{"start":{"line":13,"column":1},"end":{"line":13,"column":1}},"key":"loBXVtiRVI"},{"type":"emphasis","position":{"start":{"line":13,"column":1},"end":{"line":13,"column":1}},"children":[{"type":"text","value":"“Connect - Create - Share - Repeat”","position":{"start":{"line":13,"column":1},"end":{"line":13,"column":1}},"key":"wQX0R3LrpR"}],"key":"wu6gbLYXsX"},{"type":"text","value":" ","position":{"start":{"line":13,"column":1},"end":{"line":13,"column":1}},"key":"xUkEkHg3Vl"},{"type":"break","key":"xEhpq93rSV"},{"type":"text","value":"\nLinks to OpenGeoHub’s open science projects mentioned in the video:","position":{"start":{"line":13,"column":1},"end":{"line":13,"column":1}},"key":"MsdUyBeNBs"}],"key":"CG7OccKDj8"},{"type":"list","ordered":false,"spread":false,"position":{"start":{"line":16,"column":1},"end":{"line":18,"column":1}},"children":[{"type":"listItem","spread":true,"position":{"start":{"line":16,"column":1},"end":{"line":16,"column":1}},"children":[{"type":"paragraph","children":[{"type":"link","url":"https://opengeohub.org/","position":{"start":{"line":16,"column":1},"end":{"line":16,"column":1}},"children":[{"type":"text","value":"opengeohub","position":{"start":{"line":16,"column":1},"end":{"line":16,"column":1}},"key":"mPslwU5CXC"}],"urlSource":"https://opengeohub.org/","key":"QvPqSl49J4"}],"key":"Uvej6qmd6O"}],"key":"Cegc2goMML"},{"type":"listItem","spread":true,"position":{"start":{"line":17,"column":1},"end":{"line":17,"column":1}},"children":[{"type":"paragraph","children":[{"type":"text","value":"open environmental data cube: ","position":{"start":{"line":17,"column":1},"end":{"line":17,"column":1}},"key":"eF9h1lTmKH"},{"type":"link","url":"http://ecodatacube.eu","position":{"start":{"line":17,"column":1},"end":{"line":17,"column":1}},"children":[{"type":"text","value":"webgis","position":{"start":{"line":17,"column":1},"end":{"line":17,"column":1}},"key":"kSjMgxtCZH"}],"urlSource":"http://ecodatacube.eu","key":"CoJxNkta5T"},{"type":"text","value":", ","position":{"start":{"line":17,"column":1},"end":{"line":17,"column":1}},"key":"HvENUyGJv9"},{"type":"link","url":"http://stac.openlandmap.org","position":{"start":{"line":17,"column":1},"end":{"line":17,"column":1}},"children":[{"type":"text","value":"stac catalogue","position":{"start":{"line":17,"column":1},"end":{"line":17,"column":1}},"key":"CTZHE9kBAZ"}],"urlSource":"http://stac.openlandmap.org","key":"zwfLb5pRsF"},{"type":"text","value":", ","position":{"start":{"line":17,"column":1},"end":{"line":17,"column":1}},"key":"ObJJY7DX6t"},{"type":"link","url":"http://eumap.readthedocs.org","position":{"start":{"line":17,"column":1},"end":{"line":17,"column":1}},"children":[{"type":"text","value":"code and documentation","position":{"start":{"line":17,"column":1},"end":{"line":17,"column":1}},"key":"SfIaVKKb7s"}],"urlSource":"http://eumap.readthedocs.org","key":"zPRJglJ2uf"},{"type":"text","value":", ","position":{"start":{"line":17,"column":1},"end":{"line":17,"column":1}},"key":"NBlGVs4w9l"},{"type":"cite","url":"https://doi.org/10.7717/peerj.15478","position":{"start":{"line":17,"column":1},"end":{"line":17,"column":1}},"children":[{"type":"text","value":"publication","position":{"start":{"line":17,"column":1},"end":{"line":17,"column":1}},"key":"Lv6quOmWVj"}],"kind":"narrative","label":"Witjes_2023","identifier":"https://doi.org/10.7717/peerj.15478","enumerator":"1","key":"OUDjhXknCY"},{"type":"text","value":",","position":{"start":{"line":17,"column":1},"end":{"line":17,"column":1}},"key":"IWwAlHAQGn"}],"key":"TYILk8SbZj"}],"key":"dCHPWA7agD"},{"type":"listItem","spread":true,"position":{"start":{"line":18,"column":1},"end":{"line":18,"column":1}},"children":[{"type":"paragraph","children":[{"type":"link","url":"https://earthmonitor.org/","position":{"start":{"line":18,"column":1},"end":{"line":18,"column":1}},"children":[{"type":"text","value":"open earth monitor cyberinfrastructure","position":{"start":{"line":18,"column":1},"end":{"line":18,"column":1}},"key":"v9VTYGLzjB"}],"urlSource":"https://earthmonitor.org/","key":"YaHSjJUtgR"}],"key":"IU27fP9gFp"}],"key":"r3YQVs6A8A"}],"key":"ft050bP2hw"}],"key":"O7i5xepDIs"},{"type":"heading","depth":2,"position":{"start":{"line":20,"column":1},"end":{"line":20,"column":1}},"children":[{"type":"text","value":"The steps of your open science journey","position":{"start":{"line":20,"column":1},"end":{"line":20,"column":1}},"key":"CTKTUSiuM3"}],"identifier":"the-steps-of-your-open-science-journey","label":"The steps of your open science journey","html_id":"the-steps-of-your-open-science-journey","implicit":true,"key":"UXYOwpBTMi"},{"type":"heading","depth":3,"position":{"start":{"line":22,"column":1},"end":{"line":22,"column":1}},"children":[{"type":"text","value":"Produce your own map","position":{"start":{"line":22,"column":1},"end":{"line":22,"column":1}},"key":"Qax53ujQjV"}],"identifier":"produce-your-own-map","label":"Produce your own map","html_id":"produce-your-own-map","implicit":true,"key":"h2kmTTyYJ8"},{"type":"list","ordered":false,"spread":false,"position":{"start":{"line":23,"column":1},"end":{"line":30,"column":1}},"children":[{"type":"listItem","spread":true,"position":{"start":{"line":23,"column":1},"end":{"line":23,"column":1}},"children":[{"type":"paragraph","children":[{"type":"text","value":"Reuse the workflow to generate the snow covered area data cube","position":{"start":{"line":23,"column":1},"end":{"line":23,"column":1}},"key":"Qu9WgINw6h"}],"key":"TnMM1FHR7I"}],"key":"FQxCnFEpQG"},{"type":"listItem","spread":true,"position":{"start":{"line":24,"column":1},"end":{"line":28,"column":1}},"children":[{"type":"paragraph","children":[{"type":"text","value":"Adapt the workflow to generate your personal contribution to mapping the snow covered area of the alps","position":{"start":{"line":24,"column":1},"end":{"line":24,"column":1}},"key":"RftpnCWsWU"}],"key":"mn0sfT3sHZ"},{"type":"list","ordered":false,"spread":false,"position":{"start":{"line":25,"column":1},"end":{"line":28,"column":1}},"children":[{"type":"listItem","spread":true,"position":{"start":{"line":25,"column":1},"end":{"line":25,"column":1}},"children":[{"type":"paragraph","children":[{"type":"text","value":"Choose an extent on the map that hasn’t been mapped yet. We are producing patches of roughly 1km by 1km.","position":{"start":{"line":25,"column":1},"end":{"line":25,"column":1}},"key":"f59NOLhelf"}],"key":"OkoBCYC6Uw"}],"key":"bJNWtBricY"},{"type":"listItem","spread":true,"position":{"start":{"line":26,"column":1},"end":{"line":26,"column":1}},"children":[{"type":"paragraph","children":[{"type":"text","value":"Choose a time extent. The winter months of a given year.","position":{"start":{"line":26,"column":1},"end":{"line":26,"column":1}},"key":"PfAvqVlVL6"}],"key":"S05aHqsXxX"}],"key":"m2ASBrpDYt"},{"type":"listItem","spread":true,"position":{"start":{"line":27,"column":1},"end":{"line":27,"column":1}},"children":[{"type":"paragraph","children":[{"type":"text","value":"Add a step to reduce the time dimension. We want to create one layer for the winter season of the given year.","position":{"start":{"line":27,"column":1},"end":{"line":27,"column":1}},"key":"sHwyNeXtv3"}],"key":"OXLcoKSyjD"}],"key":"WoPx7R6fyY"},{"type":"listItem","spread":true,"position":{"start":{"line":28,"column":1},"end":{"line":28,"column":1}},"children":[{"type":"paragraph","children":[{"type":"text","value":"Adapt the file format to Cloud Optimized GeoTiff (perfectly suitable for a raster file with one time step and one band).","position":{"start":{"line":28,"column":1},"end":{"line":28,"column":1}},"key":"VQhe2UR9V8"}],"key":"NJKlzZz38N"}],"key":"GPp3M26EUJ"}],"key":"Qr0ABzUyMz"}],"key":"lJy9NATv3A"},{"type":"listItem","spread":true,"position":{"start":{"line":29,"column":1},"end":{"line":30,"column":1}},"children":[{"type":"paragraph","children":[{"type":"text","value":"Download the result consisting of the STAC metadata and the COG","position":{"start":{"line":29,"column":1},"end":{"line":29,"column":1}},"key":"ESKBS8RlHr"}],"key":"gvDAsmjdRK"}],"key":"HU9ZOp3Xe9"}],"key":"exwcMY4bRp"},{"type":"heading","depth":3,"position":{"start":{"line":31,"column":1},"end":{"line":31,"column":1}},"children":[{"type":"text","value":"Make the data FAIR and open","position":{"start":{"line":31,"column":1},"end":{"line":31,"column":1}},"key":"xtayo3mi16"}],"identifier":"make-the-data-fair-and-open","label":"Make the data FAIR and open","html_id":"make-the-data-fair-and-open","implicit":true,"key":"tse1cEy4Ji"},{"type":"iframe","src":"https://create.eo-college.org/wp-admin/admin-ajax.php?action=h5p_embed&id=18","width":"100%","title":"Cubes&Clouds: Making your data FAIR","key":"mnb8V0eIqI"},{"type":"list","ordered":false,"spread":false,"position":{"start":{"line":36,"column":1},"end":{"line":40,"column":1}},"children":[{"type":"listItem","spread":true,"position":{"start":{"line":36,"column":1},"end":{"line":36,"column":1}},"children":[{"type":"paragraph","children":[{"type":"text","value":"Customize the STAC metadata (e.g. adding you as the author)","position":{"start":{"line":36,"column":1},"end":{"line":36,"column":1}},"key":"QgrSb43obu"}],"key":"gkbufci3Ax"}],"key":"ye2J1qvJER"},{"type":"listItem","spread":true,"position":{"start":{"line":37,"column":1},"end":{"line":37,"column":1}},"children":[{"type":"paragraph","children":[{"type":"text","value":"Trigger the update of the STAC catalogue and web map by submitting your results. Your data will be openly available!","position":{"start":{"line":37,"column":1},"end":{"line":37,"column":1}},"key":"Ebotspdr6Z"}],"key":"B3NJi04JhM"}],"key":"xSBGFzG29c"},{"type":"listItem","spread":true,"position":{"start":{"line":38,"column":1},"end":{"line":38,"column":1}},"children":[{"type":"paragraph","children":[{"type":"text","value":"A license is assigned to the whole collection of all the produced patches","position":{"start":{"line":38,"column":1},"end":{"line":38,"column":1}},"key":"vJz1Z9KiD5"}],"key":"IpTwvs9cgr"}],"key":"vFm2rSj6tY"},{"type":"listItem","spread":true,"position":{"start":{"line":39,"column":1},"end":{"line":40,"column":1}},"children":[{"type":"paragraph","children":[{"type":"text","value":"A doi is assigned to the whole collection of all the produced patches","position":{"start":{"line":39,"column":1},"end":{"line":39,"column":1}},"key":"CHEm8hAO0b"}],"key":"XIeNqFhXcs"}],"key":"hp20FGEzOZ"}],"key":"W15ZTSEejM"},{"type":"heading","depth":3,"position":{"start":{"line":41,"column":1},"end":{"line":41,"column":1}},"children":[{"type":"text","value":"Evaluate how FAIR the result is","position":{"start":{"line":41,"column":1},"end":{"line":41,"column":1}},"key":"kFiqRZauG5"}],"identifier":"evaluate-how-fair-the-result-is","label":"Evaluate how FAIR the result is","html_id":"evaluate-how-fair-the-result-is","implicit":true,"key":"LwMq7E16Hd"},{"type":"list","ordered":false,"spread":false,"position":{"start":{"line":42,"column":1},"end":{"line":44,"column":1}},"children":[{"type":"listItem","spread":true,"position":{"start":{"line":42,"column":1},"end":{"line":42,"column":1}},"children":[{"type":"paragraph","children":[{"type":"text","value":"Do the FAIR self assessment tool after you’ve created your results","position":{"start":{"line":42,"column":1},"end":{"line":42,"column":1}},"key":"Aesu4YI42U"}],"key":"GWVzmTsTLc"}],"key":"x5mmgdyfVU"},{"type":"listItem","spread":true,"position":{"start":{"line":43,"column":1},"end":{"line":44,"column":1}},"children":[{"type":"paragraph","children":[{"type":"text","value":"You will get a score on how FAIR the dataset you have produced really is","position":{"start":{"line":43,"column":1},"end":{"line":43,"column":1}},"key":"iHgCfe7WEn"}],"key":"rxbyiwF6fs"}],"key":"vDUm6cKWdd"}],"key":"T0JYRFhNP2"},{"type":"heading","depth":2,"position":{"start":{"line":45,"column":1},"end":{"line":45,"column":1}},"children":[{"type":"text","value":"Exercise","position":{"start":{"line":45,"column":1},"end":{"line":45,"column":1}},"key":"zV5c75kI8y"}],"identifier":"exercise","label":"Exercise","html_id":"exercise","implicit":true,"key":"wGIy7mgYhW"},{"type":"paragraph","position":{"start":{"line":46,"column":1},"end":{"line":46,"column":1}},"children":[{"type":"text","value":"Time to start your own open science journey. Produce a snow cover area map for a region that hasn’t been mapped yet. FAIRify your results and make them publicly available! Please run both exercises, mapping different areas in each exercise.","position":{"start":{"line":46,"column":1},"end":{"line":46,"column":1}},"key":"D5FOKOZGsw"}],"key":"fnuNTVs3R1"},{"type":"paragraph","position":{"start":{"line":48,"column":1},"end":{"line":48,"column":1}},"children":[{"type":"link","url":"https://github.com/EO-College/cubes-and-clouds/blob/main/lectures/3.3_data_sharing/exercises/33_data_sharing_openeo.ipynb","position":{"start":{"line":48,"column":1},"end":{"line":48,"column":1}},"children":[{"type":"text","value":"Exercise 3.3 Sharing with openEO","position":{"start":{"line":48,"column":1},"end":{"line":48,"column":1}},"key":"UifUMEx8Md"}],"urlSource":"https://github.com/EO-College/cubes-and-clouds/blob/main/lectures/3.3_data_sharing/exercises/33_data_sharing_openeo.ipynb","data":{"kind":"file","org":"EO-College","repo":"cubes-and-clouds","reference":"main","file":"lectures/3.3_data_sharing/exercises/33_data_sharing_openeo.ipynb","raw":"https://raw.githubusercontent.com/EO-College/cubes-and-clouds/main/lectures/3.3_data_sharing/exercises/33_data_sharing_openeo.ipynb"},"internal":false,"protocol":"github","key":"kU3jr2vZ9A"}],"key":"tPXfdM5EBz"},{"type":"paragraph","position":{"start":{"line":50,"column":1},"end":{"line":50,"column":1}},"children":[{"type":"link","url":"https://github.com/EO-College/cubes-and-clouds/blob/main/lectures/3.3_data_sharing/exercises/33_data_sharing_pangeo.ipynb","position":{"start":{"line":50,"column":1},"end":{"line":50,"column":1}},"children":[{"type":"text","value":"Exercise 3.3 Sharing with Pangeo","position":{"start":{"line":50,"column":1},"end":{"line":50,"column":1}},"key":"bkg6VGbje1"}],"urlSource":"https://github.com/EO-College/cubes-and-clouds/blob/main/lectures/3.3_data_sharing/exercises/33_data_sharing_pangeo.ipynb","data":{"kind":"file","org":"EO-College","repo":"cubes-and-clouds","reference":"main","file":"lectures/3.3_data_sharing/exercises/33_data_sharing_pangeo.ipynb","raw":"https://raw.githubusercontent.com/EO-College/cubes-and-clouds/main/lectures/3.3_data_sharing/exercises/33_data_sharing_pangeo.ipynb"},"internal":false,"protocol":"github","key":"FGknTS39WX"}],"key":"gB29pkazy6"},{"type":"heading","depth":2,"position":{"start":{"line":52,"column":1},"end":{"line":52,"column":1}},"children":[{"type":"text","value":"FAIR Assessment","position":{"start":{"line":52,"column":1},"end":{"line":52,"column":1}},"key":"QQVona3Ztf"}],"identifier":"fair-assessment","label":"FAIR Assessment","html_id":"fair-assessment","implicit":true,"key":"S45HqpMUdW"},{"type":"paragraph","position":{"start":{"line":53,"column":1},"end":{"line":53,"column":1}},"children":[{"type":"text","value":"This tool allows you to check how FAIR your results are. Give it a shot!","position":{"start":{"line":53,"column":1},"end":{"line":53,"column":1}},"key":"E8T4pCqIM4"}],"key":"Ftd9um6hgJ"},{"type":"paragraph","position":{"start":{"line":55,"column":1},"end":{"line":55,"column":1}},"children":[{"type":"strong","position":{"start":{"line":55,"column":1},"end":{"line":55,"column":1}},"children":[{"type":"text","value":"Embed: ","position":{"start":{"line":55,"column":1},"end":{"line":55,"column":1}},"key":"pK3ULmc0M1"},{"type":"link","url":"https://ardc.edu.au/resource/fair-data-self-assessment-tool/","position":{"start":{"line":55,"column":1},"end":{"line":55,"column":1}},"children":[{"type":"text","value":"https://​ardc​.edu​.au​/resource​/fair​-data​-self​-assessment​-tool/","position":{"start":{"line":55,"column":1},"end":{"line":55,"column":1}},"key":"pX6Uo2iD0N"}],"urlSource":"https://ardc.edu.au/resource/fair-data-self-assessment-tool/","key":"aMWG23dvl0"}],"key":"pzM4THVO52"}],"key":"QjgizwZB1O"},{"type":"heading","depth":2,"position":{"start":{"line":57,"column":1},"end":{"line":57,"column":1}},"children":[{"type":"text","value":"Community Mapping Project","position":{"start":{"line":57,"column":1},"end":{"line":57,"column":1}},"key":"vsRTJxlXYk"}],"identifier":"community-mapping-project","label":"Community Mapping Project","html_id":"community-mapping-project","implicit":true,"key":"PboKyaz62B"},{"type":"paragraph","position":{"start":{"line":58,"column":1},"end":{"line":58,"column":1}},"children":[{"type":"text","value":"Have a look at your results! Have a look at the community mapping project you have contributed to!","position":{"start":{"line":58,"column":1},"end":{"line":58,"column":1}},"key":"PIy0DfCt21"}],"key":"RqnLPP91F5"},{"type":"paragraph","position":{"start":{"line":60,"column":1},"end":{"line":60,"column":1}},"children":[{"type":"link","url":"https://esa.pages.eox.at/cubes-and-clouds-catalog/browser/#/","position":{"start":{"line":60,"column":1},"end":{"line":60,"column":1}},"children":[{"type":"text","value":"STAC Browser Cubes and Clouds - Snow Cover","position":{"start":{"line":60,"column":1},"end":{"line":60,"column":1}},"key":"QY6JBKiHhj"}],"urlSource":"https://esa.pages.eox.at/cubes-and-clouds-catalog/browser/#/","key":"g2BL0skAAL"}],"key":"eDZLXrWiTz"},{"type":"heading","depth":2,"position":{"start":{"line":62,"column":1},"end":{"line":62,"column":1}},"children":[{"type":"text","value":"Congratulations","position":{"start":{"line":62,"column":1},"end":{"line":62,"column":1}},"key":"pKtxu9cRd1"}],"identifier":"congratulations","label":"Congratulations","html_id":"congratulations","implicit":true,"key":"qieW5umsFm"},{"type":"paragraph","position":{"start":{"line":63,"column":1},"end":{"line":63,"column":1}},"children":[{"type":"text","value":"Congrats! You’ve made it through the Cubes and Clouds online course!","position":{"start":{"line":63,"column":1},"end":{"line":63,"column":1}},"key":"MLKa7kF49W"}],"key":"veLwxoJZax"},{"type":"paragraph","position":{"start":{"line":65,"column":1},"end":{"line":65,"column":1}},"children":[{"type":"link","url":"https://youtu.be/xoCBLAPPn0k","position":{"start":{"line":65,"column":1},"end":{"line":65,"column":1}},"children":[{"type":"image","url":"/cubes-and-clouds/build/b9a0bd131aa9348dcb0b9ad02ae82c74.jpeg","alt":"Introduction to EO Cloud Platforms","position":{"start":{"line":65,"column":1},"end":{"line":65,"column":1}},"key":"Bn3DpCAEAu","urlSource":"https://img.youtube.com/vi/xoCBLAPPn0k/0.jpg"}],"urlSource":"https://youtu.be/xoCBLAPPn0k","key":"KtT1WxuREp"},{"type":"text","value":" ","position":{"start":{"line":65,"column":1},"end":{"line":65,"column":1}},"key":"suupD0MjJW"},{"type":"break","key":"ztApCYxLGA"}],"key":"ZThOPAmjXw"}],"key":"BFtyCLcDkM"}],"key":"IYKKIk0vL8"},"references":{"cite":{"order":["Witjes_2023"],"data":{"Witjes_2023":{"label":"Witjes_2023","enumerator":"1","doi":"10.7717/peerj.15478","html":"Witjes, M., Parente, L., Križan, J., Hengl, T., & Antonić, L. (2023). Ecodatacube.eu: analysis-ready open environmental data cube for Europe. <i>PeerJ</i>, <i>11</i>, e15478. <a target=\"_blank\" rel=\"noreferrer\" href=\"https://doi.org/10.7717/peerj.15478\">10.7717/peerj.15478</a>","url":"https://doi.org/10.7717/peerj.15478"}}}},"footer":{"navigation":{"prev":{"title":"3.2 Validation of the results with Pangeo","url":"/lectures/validation/exercises/validation-pangeo","group":"Process & Share"},"next":{"title":"3.3 Data Sharing with openEO","url":"/lectures/data-sharing/exercises/data-sharing-openeo","group":"Process & Share"}}},"domain":"http://localhost:3000"}