{"version":3,"kind":"Article","sha256":"f7cd37da253047c2cc9dab4db5d29172504079dd3ede4d3bec0e0f84efe99260","slug":"lectures.formats-and-performance.formats-and-performance","location":"/lectures/2.4_formats_and_performance/2.4_formats_and_performance.md","dependencies":[],"frontmatter":{"title":"Data Formats and Performance","content_includes_title":false,"github":"https://github.com/EO-college/cubes-and-clouds","subject":"Cubes and Clouds learning materials","numbering":{"title":{"offset":2}},"source_url":"https://github.com/EO-college/cubes-and-clouds/blob/main/lectures/2.4_formats_and_performance/2.4_formats_and_performance.md","edit_url":"https://github.com/EO-college/cubes-and-clouds/edit/main/lectures/2.4_formats_and_performance/2.4_formats_and_performance.md","thumbnail":"/cubes-and-clouds/build/96fdc48bce5685dcda930053ff412281.jpeg","exports":[{"format":"md","filename":"2.4_formats_and_performance.md","url":"/cubes-and-clouds/build/2.4_formats_and_perf-bdcdfbc0c59a0d81131072db635e228a.md"}]},"mdast":{"type":"root","children":[{"type":"block","children":[{"type":"heading","depth":2,"position":{"start":{"line":3,"column":1},"end":{"line":3,"column":1}},"children":[{"type":"text","value":"Learning Objectives","position":{"start":{"line":3,"column":1},"end":{"line":3,"column":1}},"key":"dQYUEbwlJ7"}],"identifier":"learning-objectives","label":"Learning Objectives","html_id":"learning-objectives","implicit":true,"key":"Nl2DitMb2e"},{"type":"list","ordered":false,"spread":false,"position":{"start":{"line":4,"column":1},"end":{"line":9,"column":1}},"children":[{"type":"listItem","spread":true,"position":{"start":{"line":4,"column":1},"end":{"line":4,"column":1}},"children":[{"type":"paragraph","children":[{"type":"text","value":"Understand what cloud native and cloud optimized data formats are","position":{"start":{"line":4,"column":1},"end":{"line":4,"column":1}},"key":"ew4CEbWsTT"}],"key":"MnZiUMvcZW"}],"key":"Bl1xD2dN7q"},{"type":"listItem","spread":true,"position":{"start":{"line":5,"column":1},"end":{"line":5,"column":1}},"children":[{"type":"paragraph","children":[{"type":"text","value":"Understand how the cloud does computing more efficiently","position":{"start":{"line":5,"column":1},"end":{"line":5,"column":1}},"key":"daD5ebqwCM"}],"key":"rU53KypZdq"}],"key":"cDdfkVgwYr"},{"type":"listItem","spread":true,"position":{"start":{"line":6,"column":1},"end":{"line":6,"column":1}},"children":[{"type":"paragraph","children":[{"type":"text","value":"Understand chunking","position":{"start":{"line":6,"column":1},"end":{"line":6,"column":1}},"key":"ZgL1TNiKrM"}],"key":"l6jGVgqJXh"}],"key":"uNmc8n9SAC"},{"type":"listItem","spread":true,"position":{"start":{"line":7,"column":1},"end":{"line":9,"column":1}},"children":[{"type":"paragraph","children":[{"type":"text","value":"Understand how chunking impact performance","position":{"start":{"line":7,"column":1},"end":{"line":7,"column":1}},"key":"YllNODkW8J"}],"key":"tB4YoZQDNO"}],"key":"t8ABrfonea"}],"key":"dTdO4rX3al"},{"type":"heading","depth":2,"position":{"start":{"line":10,"column":1},"end":{"line":10,"column":1}},"children":[{"type":"text","value":"Outline","position":{"start":{"line":10,"column":1},"end":{"line":10,"column":1}},"key":"KmZAGlgXDE"}],"identifier":"outline","label":"Outline","html_id":"outline","implicit":true,"key":"JevJh7mi8o"},{"type":"list","ordered":false,"spread":false,"position":{"start":{"line":11,"column":1},"end":{"line":21,"column":1}},"children":[{"type":"listItem","spread":true,"position":{"start":{"line":11,"column":1},"end":{"line":15,"column":1}},"children":[{"type":"paragraph","children":[{"type":"text","value":"Cloud Native and Cloud Optimized Data Formats","position":{"start":{"line":11,"column":1},"end":{"line":11,"column":1}},"key":"mVPJRJgFyU"}],"key":"dL5va3YYin"},{"type":"list","ordered":false,"spread":false,"position":{"start":{"line":12,"column":1},"end":{"line":15,"column":1}},"children":[{"type":"listItem","spread":true,"position":{"start":{"line":12,"column":1},"end":{"line":12,"column":1}},"children":[{"type":"paragraph","children":[{"type":"text","value":"Why do we need them","position":{"start":{"line":12,"column":1},"end":{"line":12,"column":1}},"key":"vVFzdPdmcK"}],"key":"Oh4K9bx5fB"}],"key":"EbCNMD41Hu"},{"type":"listItem","spread":true,"position":{"start":{"line":13,"column":1},"end":{"line":13,"column":1}},"children":[{"type":"paragraph","children":[{"type":"text","value":"What is their advantage over classical file formats","position":{"start":{"line":13,"column":1},"end":{"line":13,"column":1}},"key":"Sib8YwW342"}],"key":"sm04smcIRz"}],"key":"LrGzc5E8tv"},{"type":"listItem","spread":true,"position":{"start":{"line":14,"column":1},"end":{"line":14,"column":1}},"children":[{"type":"paragraph","children":[{"type":"text","value":"Not one format to rule them all.","position":{"start":{"line":14,"column":1},"end":{"line":14,"column":1}},"key":"kzyZNMzipq"}],"key":"pkBqvIy7dG"}],"key":"omTSDKvhwT"},{"type":"listItem","spread":true,"position":{"start":{"line":15,"column":1},"end":{"line":15,"column":1}},"children":[{"type":"paragraph","children":[{"type":"text","value":"Examples","position":{"start":{"line":15,"column":1},"end":{"line":15,"column":1}},"key":"DHgAOhd0Nr"}],"key":"LRATl7KPuH"}],"key":"vEH5XOVOZ0"}],"key":"cKjK8R4pmg"}],"key":"V8DfUzdv6L"},{"type":"listItem","spread":true,"position":{"start":{"line":16,"column":1},"end":{"line":21,"column":1}},"children":[{"type":"paragraph","children":[{"type":"text","value":"Performance in the cloud","position":{"start":{"line":16,"column":1},"end":{"line":16,"column":1}},"key":"zlpvmhp9OT"}],"key":"DWm9fc7YbT"},{"type":"list","ordered":false,"spread":false,"position":{"start":{"line":17,"column":1},"end":{"line":21,"column":1}},"children":[{"type":"listItem","spread":true,"position":{"start":{"line":17,"column":1},"end":{"line":17,"column":1}},"children":[{"type":"paragraph","children":[{"type":"text","value":"Tiling","position":{"start":{"line":17,"column":1},"end":{"line":17,"column":1}},"key":"GStgTS3eLV"}],"key":"UW3KrluwA2"}],"key":"oMC1m56dJr"},{"type":"listItem","spread":true,"position":{"start":{"line":18,"column":1},"end":{"line":18,"column":1}},"children":[{"type":"paragraph","children":[{"type":"text","value":"Chunking","position":{"start":{"line":18,"column":1},"end":{"line":18,"column":1}},"key":"acO0Tj7SHw"}],"key":"Mty2RdR6U0"}],"key":"wrljNRSfVg"},{"type":"listItem","spread":true,"position":{"start":{"line":19,"column":1},"end":{"line":19,"column":1}},"children":[{"type":"paragraph","children":[{"type":"text","value":"Cost of Scalability","position":{"start":{"line":19,"column":1},"end":{"line":19,"column":1}},"key":"HyL6wGstGj"}],"key":"Tie7YfDa2m"}],"key":"hG6b4OLENS"},{"type":"listItem","spread":true,"position":{"start":{"line":20,"column":1},"end":{"line":21,"column":1}},"children":[{"type":"paragraph","children":[{"type":"text","value":"Distributed Computing","position":{"start":{"line":20,"column":1},"end":{"line":20,"column":1}},"key":"alCir6cDQI"}],"key":"HtSetjZO75"}],"key":"Mw12QUPUCA"}],"key":"XbK3J7bONz"}],"key":"kuw0REvXaH"}],"key":"WtAZsVBiYl"},{"type":"heading","depth":2,"position":{"start":{"line":22,"column":1},"end":{"line":22,"column":1}},"children":[{"type":"text","value":"Cloud Native and Cloud Optimized Data Formats","position":{"start":{"line":22,"column":1},"end":{"line":22,"column":1}},"key":"ljrcMKnau5"}],"identifier":"cloud-native-and-cloud-optimized-data-formats","label":"Cloud Native and Cloud Optimized Data Formats","html_id":"cloud-native-and-cloud-optimized-data-formats","implicit":true,"key":"gpzC4WGbzz"},{"type":"heading","depth":3,"position":{"start":{"line":24,"column":1},"end":{"line":24,"column":1}},"children":[{"type":"text","value":"Why do we need them","position":{"start":{"line":24,"column":1},"end":{"line":24,"column":1}},"key":"TIUgrPuvfL"}],"identifier":"why-do-we-need-them","label":"Why do we need them","html_id":"why-do-we-need-them","implicit":true,"key":"ACDdq60Uhd"},{"type":"paragraph","position":{"start":{"line":25,"column":1},"end":{"line":25,"column":1}},"children":[{"type":"text","value":"Cloud native and cloud optimized formats have been specifically designed to optimize the storage, access and processing in cloud computing environments. The main difference between cloud optimized and cloud native comes from their origin: the first are an optimized version of an existing file format whereas the latter have been designed to be efficient for a cloud usage from the beginning. These formats are tailored to leverage the scalability, flexibility, and parallel processing capabilities of a cloud infrastructure, enabling efficient handling of large-scale datasets.","position":{"start":{"line":25,"column":1},"end":{"line":25,"column":1}},"key":"URikxLmIFS"}],"key":"gqdqFhZj1M"},{"type":"paragraph","position":{"start":{"line":27,"column":1},"end":{"line":27,"column":1}},"children":[{"type":"link","url":"https://www.youtube.com/watch?v=hxv3LxsdGhw","position":{"start":{"line":27,"column":1},"end":{"line":27,"column":1}},"children":[{"type":"image","url":"/cubes-and-clouds/build/96fdc48bce5685dcda930053ff412281.jpeg","alt":"Cloud Native Data Formats","position":{"start":{"line":27,"column":1},"end":{"line":27,"column":1}},"key":"RMI1L4Mg07","urlSource":"https://img.youtube.com/vi/hxv3LxsdGhw/0.jpg"}],"urlSource":"https://www.youtube.com/watch?v=hxv3LxsdGhw","key":"UmpqycZi1k"},{"type":"text","value":" ","position":{"start":{"line":27,"column":1},"end":{"line":27,"column":1}},"key":"LM4w1evLCd"},{"type":"break","key":"Pa5TWWENlr"}],"key":"YB3PcTJOzj"},{"type":"blockquote","position":{"start":{"line":28,"column":1},"end":{"line":29,"column":1}},"children":[{"type":"paragraph","position":{"start":{"line":28,"column":1},"end":{"line":29,"column":1}},"children":[{"type":"text","value":"Video content in cooperation with ","position":{"start":{"line":28,"column":1},"end":{"line":28,"column":1}},"key":"x3kmbhRk5J"},{"type":"link","url":"https://developmentseed.org/team/aimee-barciauskas","position":{"start":{"line":28,"column":1},"end":{"line":28,"column":1}},"children":[{"type":"text","value":"Aimee Barciauskas","position":{"start":{"line":28,"column":1},"end":{"line":28,"column":1}},"key":"lYYaWMWhX0"}],"urlSource":"https://developmentseed.org/team/aimee-barciauskas","key":"GX3dKm1RdE"},{"type":"text","value":" (DevelopmentSeed) and ","position":{"start":{"line":28,"column":1},"end":{"line":28,"column":1}},"key":"CGsplfieSD"},{"type":"link","url":"https://developmentseed.org/team/ryan-avery","position":{"start":{"line":28,"column":1},"end":{"line":28,"column":1}},"children":[{"type":"text","value":"Ryan Avery","position":{"start":{"line":28,"column":1},"end":{"line":28,"column":1}},"key":"ERUt9A160a"}],"urlSource":"https://developmentseed.org/team/ryan-avery","key":"AbkvfmIUTo"},{"type":"text","value":" (DevelopmentSeed). ","position":{"start":{"line":28,"column":1},"end":{"line":28,"column":1}},"key":"cH2KY8EUTs"},{"type":"break","key":"KgYJlZvmSB"},{"type":"text","value":"\n","position":{"start":{"line":28,"column":1},"end":{"line":28,"column":1}},"key":"B03AntJx3K"},{"type":"emphasis","position":{"start":{"line":28,"column":1},"end":{"line":28,"column":1}},"children":[{"type":"text","value":"“Cloud-optimized means organizing so subsets of data can be read. Ideally, the data is also compressed. Both of these factors minimize the amount of data that has to be transferred across a network.”","position":{"start":{"line":28,"column":1},"end":{"line":28,"column":1}},"key":"ZCoanZaue3"}],"key":"QwqhNP91X0"}],"key":"t6P0gWpUHy"}],"key":"UGnTez2ViT"},{"type":"heading","depth":3,"position":{"start":{"line":31,"column":1},"end":{"line":31,"column":1}},"children":[{"type":"text","value":"Characteristics","position":{"start":{"line":31,"column":1},"end":{"line":31,"column":1}},"key":"nnAZp6JXVh"}],"identifier":"characteristics","label":"Characteristics","html_id":"characteristics","implicit":true,"key":"kDTj2UGss3"},{"type":"paragraph","position":{"start":{"line":32,"column":1},"end":{"line":32,"column":1}},"children":[{"type":"text","value":"Cloud native and cloud optimized means mainly optimized read access, and more specifically partial and parallel reads capabilities. The main common characteristics are listed below.","position":{"start":{"line":32,"column":1},"end":{"line":32,"column":1}},"key":"KFNOmaxZps"}],"key":"FBN1riAhhb"},{"type":"heading","depth":4,"position":{"start":{"line":34,"column":1},"end":{"line":34,"column":1}},"children":[{"type":"text","value":"Data Chunking","position":{"start":{"line":34,"column":1},"end":{"line":34,"column":1}},"key":"gpoZPXHi3s"}],"identifier":"data-chunking","label":"Data Chunking","html_id":"data-chunking","implicit":true,"key":"JIE9QL0VFY"},{"type":"paragraph","position":{"start":{"line":35,"column":1},"end":{"line":35,"column":1}},"children":[{"type":"text","value":"When working with large data files or collections, it’s often impossible to load all the data into a single computer’s memory at once. In such cases, a data chunking approach can be highly effective. By dividing the dataset into smaller ","position":{"start":{"line":35,"column":1},"end":{"line":35,"column":1}},"key":"S7lnGCTL6e"},{"type":"strong","position":{"start":{"line":35,"column":1},"end":{"line":35,"column":1}},"children":[{"type":"text","value":"chunks","position":{"start":{"line":35,"column":1},"end":{"line":35,"column":1}},"key":"f8D06A5nXt"}],"key":"pheBJs8fDM"},{"type":"text","value":", the data can be processed piece by piece without exceeding the computer’s memory capacity. This approach is particularly useful for managing large datasets on a single machine and can also scale to distributed computing environments, such as cloud platforms or high-performance computing systems.","position":{"start":{"line":35,"column":1},"end":{"line":35,"column":1}},"key":"M3azRkkfIE"}],"key":"nCnVBJ387F"},{"type":"paragraph","position":{"start":{"line":37,"column":1},"end":{"line":37,"column":1}},"children":[{"type":"text","value":"The ","position":{"start":{"line":37,"column":1},"end":{"line":37,"column":1}},"key":"UdEwqqJSqj"},{"type":"strong","position":{"start":{"line":37,"column":1},"end":{"line":37,"column":1}},"children":[{"type":"text","value":"chunk","position":{"start":{"line":37,"column":1},"end":{"line":37,"column":1}},"key":"YQvLAENIUa"}],"key":"OihBw5GQB7"},{"type":"text","value":" is the smallest atomic unit of a larger dataset that can be processed independently, enabling efficient data handling by dividing the dataset into manageable pieces enabling parallel processing and efficient retrieval of specific portions of the data, reducing the need to access the entire dataset.","position":{"start":{"line":37,"column":1},"end":{"line":37,"column":1}},"key":"Eikl7Qi7TO"}],"key":"aXCNFVaYXH"},{"type":"paragraph","position":{"start":{"line":39,"column":1},"end":{"line":39,"column":1}},"children":[{"type":"text","value":"The figure below visually explains the concept of data chunking: on the left, a three-dimensional data cube (x, y, and time) is shown without chunks, while on the right, the same data cube is displayed with chunks highlighted.","position":{"start":{"line":39,"column":1},"end":{"line":39,"column":1}},"key":"HagMfsqgYP"}],"key":"isz8H7CIdQ"},{"type":"table","position":{"start":{"line":41,"column":1},"end":{"line":43,"column":1}},"children":[{"type":"tableRow","position":{"start":{"line":41,"column":1},"end":{"line":41,"column":1}},"children":[{"type":"tableCell","header":true,"position":{"start":{"line":41,"column":1},"end":{"line":41,"column":1}},"children":[{"type":"text","value":"Data Cube without chunking","position":{"start":{"line":41,"column":1},"end":{"line":41,"column":1}},"key":"MH8Jf1Mt2G"}],"key":"qbuCyKaCRB"},{"type":"tableCell","header":true,"position":{"start":{"line":41,"column":1},"end":{"line":41,"column":1}},"children":[{"type":"text","value":"Data Cube with chunking","position":{"start":{"line":41,"column":1},"end":{"line":41,"column":1}},"key":"RJNkmA9LTa"}],"key":"y6aDjv7tHa"}],"key":"DiAqRbVMQU"},{"type":"tableRow","position":{"start":{"line":43,"column":1},"end":{"line":43,"column":1}},"children":[{"type":"tableCell","position":{"start":{"line":43,"column":1},"end":{"line":43,"column":1}},"children":[{"type":"image","url":"/cubes-and-clouds/build/notchunked-09a097c5a55cd12dd8047ed9c0054947.png","alt":"No Chunking","title":"Data Cube without chunking","position":{"start":{"line":43,"column":1},"end":{"line":43,"column":1}},"key":"Ad4qRAIgsv","urlSource":"./exercises/assets/notchunked.png"}],"key":"qmpMQfUGwX"},{"type":"tableCell","position":{"start":{"line":43,"column":1},"end":{"line":43,"column":1}},"children":[{"type":"image","url":"/cubes-and-clouds/build/chunked-e247d309c09cb31bedd424c2d5fd6988.png","alt":"Chunking","title":"Data Cube with chunking","position":{"start":{"line":43,"column":1},"end":{"line":43,"column":1}},"key":"jDCqLQX7eo","urlSource":"./exercises/assets/chunked.png"}],"key":"mZdjh1Ind4"}],"key":"WBUdFfoEYi"}],"key":"DaPFZEi0iX"},{"type":"blockquote","position":{"start":{"line":45,"column":1},"end":{"line":45,"column":1}},"children":[{"type":"paragraph","position":{"start":{"line":45,"column":1},"end":{"line":45,"column":1}},"children":[{"type":"text","value":"Figure: on the left, a 3D data cube without any chunking strategy applied. On the right, a 3D data cube with box chunking.","position":{"start":{"line":45,"column":1},"end":{"line":45,"column":1}},"key":"G5jiFADpKb"}],"key":"dYsH4onoYQ"}],"key":"xAXKF405d1"},{"type":"paragraph","position":{"start":{"line":47,"column":1},"end":{"line":47,"column":1}},"children":[{"type":"text","value":"There are different ways to chunk data, depending on the nature of the dataset and the analysis requirements.","position":{"start":{"line":47,"column":1},"end":{"line":47,"column":1}},"key":"RGDXhNqpyC"}],"key":"ohJi5xl0vA"},{"type":"list","ordered":false,"spread":false,"position":{"start":{"line":49,"column":1},"end":{"line":52,"column":1}},"children":[{"type":"listItem","spread":true,"position":{"start":{"line":49,"column":1},"end":{"line":49,"column":1}},"children":[{"type":"paragraph","children":[{"type":"strong","position":{"start":{"line":49,"column":1},"end":{"line":49,"column":1}},"children":[{"type":"text","value":"Spatial chunking","position":{"start":{"line":49,"column":1},"end":{"line":49,"column":1}},"key":"UQn0hMdIek"}],"key":"satNFgpecT"},{"type":"text","value":" divides data based on geographical or spatial dimensions (e.g., longitude, latitude), which is ideal for geospatial datasets where the data is naturally distributed across space.","position":{"start":{"line":49,"column":1},"end":{"line":49,"column":1}},"key":"XSXaDmIKyA"}],"key":"sWpUZkqisp"}],"key":"r0UA7p4nGC"},{"type":"listItem","spread":true,"position":{"start":{"line":50,"column":1},"end":{"line":50,"column":1}},"children":[{"type":"paragraph","children":[{"type":"strong","position":{"start":{"line":50,"column":1},"end":{"line":50,"column":1}},"children":[{"type":"text","value":"Time-based chunking","position":{"start":{"line":50,"column":1},"end":{"line":50,"column":1}},"key":"GQbIY3yeZd"}],"key":"eOM7hNBxng"},{"type":"text","value":" focuses on temporal dimensions (e.g., by day, month, or year), which is suitable for time-series data.","position":{"start":{"line":50,"column":1},"end":{"line":50,"column":1}},"key":"bDgihY7Fy6"}],"key":"MGJ6Wx5Jic"}],"key":"QMy8FnWDa2"},{"type":"listItem","spread":true,"position":{"start":{"line":51,"column":1},"end":{"line":52,"column":1}},"children":[{"type":"paragraph","children":[{"type":"strong","position":{"start":{"line":51,"column":1},"end":{"line":51,"column":1}},"children":[{"type":"text","value":"Box chunking","position":{"start":{"line":51,"column":1},"end":{"line":51,"column":1}},"key":"ZnfqVdeHH0"}],"key":"NmyfxBx8aY"},{"type":"text","value":" divides the data into fixed-size blocks (e.g., cubes or boxes), providing a balance between spatial and time-based chunking.","position":{"start":{"line":51,"column":1},"end":{"line":51,"column":1}},"key":"psgvSgS9kg"}],"key":"njsomcpcIQ"}],"key":"BihxzBpKiV"}],"key":"THls8BQBs5"},{"type":"paragraph","position":{"start":{"line":53,"column":1},"end":{"line":53,"column":1}},"children":[{"type":"text","value":"The choice of chunking strategy can significantly impact the efficiency of data access. Spatial chunking is optimal for spatial queries, while time-based chunking improves access to time-series data. Using the right chunking strategy can reduce the computational overhead and improve the overall performance of data processing tasks.","position":{"start":{"line":53,"column":1},"end":{"line":53,"column":1}},"key":"L3CeEuwBZG"}],"key":"pfMF8S8QuY"},{"type":"paragraph","position":{"start":{"line":55,"column":1},"end":{"line":55,"column":1}},"children":[{"type":"text","value":"The image below illustrates the two most current chunking strategies:","position":{"start":{"line":55,"column":1},"end":{"line":55,"column":1}},"key":"EQRlPA4brP"}],"key":"HgDrUA55A8"},{"type":"table","position":{"start":{"line":57,"column":1},"end":{"line":59,"column":1}},"children":[{"type":"tableRow","position":{"start":{"line":57,"column":1},"end":{"line":57,"column":1}},"children":[{"type":"tableCell","header":true,"position":{"start":{"line":57,"column":1},"end":{"line":57,"column":1}},"children":[{"type":"text","value":"Spatial chunking strategy","position":{"start":{"line":57,"column":1},"end":{"line":57,"column":1}},"key":"cVCRHhkysF"}],"key":"dfSmAkFkb3"},{"type":"tableCell","header":true,"position":{"start":{"line":57,"column":1},"end":{"line":57,"column":1}},"children":[{"type":"text","value":"Box chunking strategy","position":{"start":{"line":57,"column":1},"end":{"line":57,"column":1}},"key":"CJYcKMx48r"}],"key":"B3GAOA5jnP"}],"key":"IQZRYmJcBK"},{"type":"tableRow","position":{"start":{"line":59,"column":1},"end":{"line":59,"column":1}},"children":[{"type":"tableCell","position":{"start":{"line":59,"column":1},"end":{"line":59,"column":1}},"children":[{"type":"image","url":"/cubes-and-clouds/build/spatialchunking-260f2774eca6da9e795da241114adeb3.png","alt":"Spatial Chunking","title":"Data Cube with spatial chunking","position":{"start":{"line":59,"column":1},"end":{"line":59,"column":1}},"key":"i5cQDTy7Mz","urlSource":"./exercises/assets/spatialchunking.png"}],"key":"DcgITwNRFm"},{"type":"tableCell","position":{"start":{"line":59,"column":1},"end":{"line":59,"column":1}},"children":[{"type":"image","url":"/cubes-and-clouds/build/boxchunking-9c5fa20e089b4cc154afae03ad35b273.png","alt":"Box Chunking","title":"Data Cube with box chunking","position":{"start":{"line":59,"column":1},"end":{"line":59,"column":1}},"key":"lOECBRoSOC","urlSource":"./exercises/assets/boxchunking.png"}],"key":"MWrZJNHD7L"}],"key":"Rox5KrIHwl"}],"key":"Q7CE4Ov70O"},{"type":"blockquote","position":{"start":{"line":61,"column":1},"end":{"line":61,"column":1}},"children":[{"type":"paragraph","position":{"start":{"line":61,"column":1},"end":{"line":61,"column":1}},"children":[{"type":"text","value":"Figure: on the left, a 3D data cube with spatial chunking. On the right, a 3D data cube with box chunking.","position":{"start":{"line":61,"column":1},"end":{"line":61,"column":1}},"key":"wxSD0Gw8Q2"}],"key":"oZBPZmeRH2"}],"key":"JxM1dHQD7Y"},{"type":"heading","depth":4,"position":{"start":{"line":63,"column":1},"end":{"line":63,"column":1}},"children":[{"type":"text","value":"Data Tiling","position":{"start":{"line":63,"column":1},"end":{"line":63,"column":1}},"key":"kiBLtdcJrB"}],"identifier":"data-tiling","label":"Data Tiling","html_id":"data-tiling","implicit":true,"key":"oRXkUm8i81"},{"type":"paragraph","position":{"start":{"line":64,"column":1},"end":{"line":65,"column":1}},"children":[{"type":"text","value":"Tiling strategies are used to divide the data into smaller, manageable tiles that can be independently accessed and processed.\nData tiling is similar to chunking, but specifically suited for Raster images, web maps, and tiled datasets (e.g., Web Map Tiles, Cloud-Optimized GeoTIFFs). It divides spatial data into smaller, regularly shaped regions (usually squares or rectangles) to optimize visualization and retrieval. It allows efficient loading and rendering of specific map sections without loading the entire dataset and allows access by geographic location (e.g., XYZ tiles in a web map).","position":{"start":{"line":64,"column":1},"end":{"line":64,"column":1}},"key":"BMdlpFDH9x"}],"key":"vbqPNWn9u6"},{"type":"heading","depth":4,"position":{"start":{"line":67,"column":1},"end":{"line":67,"column":1}},"children":[{"type":"text","value":"Internal Indexing","position":{"start":{"line":67,"column":1},"end":{"line":67,"column":1}},"key":"WGPejnr06b"}],"identifier":"internal-indexing","label":"Internal Indexing","html_id":"internal-indexing","implicit":true,"key":"AxaJAWmO6v"},{"type":"paragraph","position":{"start":{"line":68,"column":1},"end":{"line":68,"column":1}},"children":[{"type":"text","value":"These formats incorporate internal indexing structures that facilitate fast spatial and attribute queries. This enables efficient data access and retrieval operations without the need for extensive scanning or processing of the entire dataset.","position":{"start":{"line":68,"column":1},"end":{"line":68,"column":1}},"key":"kuSTchRrG5"}],"key":"yGZ5KMj6Tc"},{"type":"heading","depth":4,"position":{"start":{"line":70,"column":1},"end":{"line":70,"column":1}},"children":[{"type":"text","value":"Metadata Optimization","position":{"start":{"line":70,"column":1},"end":{"line":70,"column":1}},"key":"DeX1bkne9v"}],"identifier":"metadata-optimization","label":"Metadata Optimization","html_id":"metadata-optimization","implicit":true,"key":"H15sqgy4gd"},{"type":"paragraph","position":{"start":{"line":71,"column":1},"end":{"line":71,"column":1}},"children":[{"type":"text","value":"The metadata is optimized for storage and indexing, allowing for efficient access and retrieval of metadata associated with the data at once. This supports faster discovery and interpretation of data properties and characteristics.","position":{"start":{"line":71,"column":1},"end":{"line":71,"column":1}},"key":"g4l6bP05IQ"}],"key":"HhCBvJlQVQ"},{"type":"heading","depth":4,"position":{"start":{"line":73,"column":1},"end":{"line":73,"column":1}},"children":[{"type":"text","value":"Compression","position":{"start":{"line":73,"column":1},"end":{"line":73,"column":1}},"key":"YZ3dN3NWd0"}],"identifier":"compression","label":"Compression","html_id":"compression","implicit":true,"key":"nx5QPQXw7F"},{"type":"paragraph","position":{"start":{"line":74,"column":1},"end":{"line":74,"column":1}},"children":[{"type":"text","value":"Advanced compression techniques are often applied to reduce storage requirements while maintaining data quality.","position":{"start":{"line":74,"column":1},"end":{"line":74,"column":1}},"key":"mz8W6TiO56"}],"key":"jTrEourWTt"},{"type":"heading","depth":3,"position":{"start":{"line":76,"column":1},"end":{"line":76,"column":1}},"children":[{"type":"text","value":"Examples of cloud native and cloud optimized raster and multi-dimensional array formats","position":{"start":{"line":76,"column":1},"end":{"line":76,"column":1}},"key":"DzTBZ1vfXk"}],"identifier":"examples-of-cloud-native-and-cloud-optimized-raster-and-multi-dimensional-array-formats","label":"Examples of cloud native and cloud optimized raster and multi-dimensional array formats","html_id":"examples-of-cloud-native-and-cloud-optimized-raster-and-multi-dimensional-array-formats","implicit":true,"key":"MxJ9oUcvyN"},{"type":"list","ordered":false,"spread":false,"position":{"start":{"line":78,"column":1},"end":{"line":83,"column":1}},"children":[{"type":"listItem","spread":true,"position":{"start":{"line":78,"column":1},"end":{"line":79,"column":1}},"children":[{"type":"paragraph","position":{"start":{"line":78,"column":1},"end":{"line":78,"column":1}},"children":[{"type":"strong","position":{"start":{"line":78,"column":1},"end":{"line":78,"column":1}},"children":[{"type":"text","value":"Zarr","position":{"start":{"line":78,"column":1},"end":{"line":78,"column":1}},"key":"mf0G6CN07R"}],"key":"H8GuFn71m4"},{"type":"text","value":" is a format specifically designed for storing and accessing multidimensional arrays. It supports chunking, compression, and parallel processing, making it suitable for large-scale geospatial datasets, for example, weather data. Metadata is stored externally in data files itself. Tt can be considered the cloud evolution of netCDF, which is instead optimized for local/HPC storage.","position":{"start":{"line":78,"column":1},"end":{"line":78,"column":1}},"key":"af4VyjNzmo"}],"key":"VBlFl3CU1G"}],"key":"RVQObcBlxB"},{"type":"listItem","spread":true,"position":{"start":{"line":80,"column":1},"end":{"line":81,"column":1}},"children":[{"type":"paragraph","position":{"start":{"line":80,"column":1},"end":{"line":80,"column":1}},"children":[{"type":"strong","position":{"start":{"line":80,"column":1},"end":{"line":80,"column":1}},"children":[{"type":"text","value":"Cloud-Optimized GeoTIFF (COG)","position":{"start":{"line":80,"column":1},"end":{"line":80,"column":1}},"key":"s4yjRXuXcv"}],"key":"Mk02iiGf6r"},{"type":"text","value":" is an optimized version of the GeoTIFF format. It organizes raster data into chunks, utilizes internal tiling and compression, and uses HTTP range requests for efficient data access in the cloud. HTTP Range Request allows clients to request only a specific portion or range of data instead of a complete dataset.","position":{"start":{"line":80,"column":1},"end":{"line":80,"column":1}},"key":"T4bUse77U2"}],"key":"ClQ0hgvvbN"}],"key":"milWPg1Mc1"},{"type":"listItem","spread":true,"position":{"start":{"line":82,"column":1},"end":{"line":83,"column":1}},"children":[{"type":"paragraph","position":{"start":{"line":82,"column":1},"end":{"line":82,"column":1}},"children":[{"type":"strong","position":{"start":{"line":82,"column":1},"end":{"line":82,"column":1}},"children":[{"type":"text","value":"TileDB","position":{"start":{"line":82,"column":1},"end":{"line":82,"column":1}},"key":"XtOdVlFBX6"}],"key":"e7ALwseiLX"},{"type":"text","value":" is a multi-dimensional, cloud-first format that supports array-based geospatial data.","position":{"start":{"line":82,"column":1},"end":{"line":82,"column":1}},"key":"NsdhdVqqZT"}],"key":"od4zNecg4s"}],"key":"riSxFO39wU"}],"key":"wTxrJ2B3LC"},{"type":"heading","depth":3,"position":{"start":{"line":84,"column":1},"end":{"line":84,"column":1}},"children":[{"type":"text","value":"Examples of cloud native and cloud optimized vector formats","position":{"start":{"line":84,"column":1},"end":{"line":84,"column":1}},"key":"k7U8BQHfJE"}],"identifier":"examples-of-cloud-native-and-cloud-optimized-vector-formats","label":"Examples of cloud native and cloud optimized vector formats","html_id":"examples-of-cloud-native-and-cloud-optimized-vector-formats","implicit":true,"key":"xb5zlaTjI1"},{"type":"list","ordered":false,"spread":false,"position":{"start":{"line":86,"column":1},"end":{"line":89,"column":1}},"children":[{"type":"listItem","spread":true,"position":{"start":{"line":86,"column":1},"end":{"line":87,"column":1}},"children":[{"type":"paragraph","position":{"start":{"line":86,"column":1},"end":{"line":86,"column":1}},"children":[{"type":"strong","position":{"start":{"line":86,"column":1},"end":{"line":86,"column":1}},"children":[{"type":"text","value":"FlatGeoBuf","position":{"start":{"line":86,"column":1},"end":{"line":86,"column":1}},"key":"qSisw2Zhc2"}],"key":"NJs80BR5U9"},{"type":"text","value":" is a cloud optimized vector data format. It is a binary encoding format for geodata and holds a collection of Simple Features.","position":{"start":{"line":86,"column":1},"end":{"line":86,"column":1}},"key":"vOxP0j6B0P"}],"key":"e4sAPSe4na"}],"key":"FSyKdcDKdF"},{"type":"listItem","spread":true,"position":{"start":{"line":88,"column":1},"end":{"line":89,"column":1}},"children":[{"type":"paragraph","position":{"start":{"line":88,"column":1},"end":{"line":88,"column":1}},"children":[{"type":"strong","position":{"start":{"line":88,"column":1},"end":{"line":88,"column":1}},"children":[{"type":"text","value":"GeoParquet","position":{"start":{"line":88,"column":1},"end":{"line":88,"column":1}},"key":"Mh9j8f7KE0"}],"key":"bpmNXPaG1J"},{"type":"text","value":" is a columnar, optimized tabular geospatial format leveraging Parquet, allowing efficient querying in cloud-based analytics.","position":{"start":{"line":88,"column":1},"end":{"line":88,"column":1}},"key":"fSpp7uxBQH"}],"key":"xXqrufQ0fH"}],"key":"lTmkjJSelq"}],"key":"f4vlZgonTC"},{"type":"paragraph","position":{"start":{"line":90,"column":1},"end":{"line":90,"column":1}},"children":[{"type":"text","value":"These two formats can be used replace the ","position":{"start":{"line":90,"column":1},"end":{"line":90,"column":1}},"key":"w7JM6vdWfU"},{"type":"strong","position":{"start":{"line":90,"column":1},"end":{"line":90,"column":1}},"children":[{"type":"text","value":"Shapefile (SHP)","position":{"start":{"line":90,"column":1},"end":{"line":90,"column":1}},"key":"qSMr81W787"}],"key":"OnlH8p1tPH"},{"type":"text","value":" format, which is a widely used but outdated vector data format that stores geospatial features in multiple files (.shp, .dbf, .shx). While still supported in many GIS applications, it has limitations such as file size restrictions (4GB limit), lack of support for modern cloud storage, and inefficiency in querying large datasets.","position":{"start":{"line":90,"column":1},"end":{"line":90,"column":1}},"key":"wupECAti44"}],"key":"NbwuMa68Tk"},{"type":"paragraph","position":{"start":{"line":92,"column":1},"end":{"line":92,"column":1}},"children":[{"type":"text","value":"Connect the cloud native data format and it’s predecessor to it’s spatial data type:","position":{"start":{"line":92,"column":1},"end":{"line":92,"column":1}},"key":"dcYL78GUiN"}],"key":"aibESjNiwJ"},{"type":"iframe","src":"https://create.eo-college.org/wp-admin/admin-ajax.php?action=h5p_embed&id=10","width":"100%","title":"Cubes&Clouds: Cloud Native Data Formats","key":"kBsBFMHvBB"},{"type":"heading","depth":3,"position":{"start":{"line":97,"column":1},"end":{"line":97,"column":1}},"children":[{"type":"text","value":"Available Material","position":{"start":{"line":97,"column":1},"end":{"line":97,"column":1}},"key":"ob5jdmXdKp"}],"identifier":"available-material","label":"Available Material","html_id":"available-material","implicit":true,"key":"GUzDh0rYgN"},{"type":"list","ordered":false,"spread":false,"position":{"start":{"line":98,"column":1},"end":{"line":109,"column":1}},"children":[{"type":"listItem","spread":true,"position":{"start":{"line":98,"column":1},"end":{"line":98,"column":1}},"children":[{"type":"paragraph","children":[{"type":"text","value":"Ryan Avery, Aimee Barciauskas, Development Seed, United States (2023). Technologies used to Create, Store and Access Geospatial Data in the Cloud. ","position":{"start":{"line":98,"column":1},"end":{"line":98,"column":1}},"key":"vQqM0bPsrO"},{"type":"link","url":"https://2023.ieeeigarss.org/view_paper.php?PaperNum=5306","position":{"start":{"line":98,"column":1},"end":{"line":98,"column":1}},"children":[{"type":"text","value":"https://​2023​.ieeeigarss​.org​/view​_paper​.php​?PaperNum​=​5306","position":{"start":{"line":98,"column":1},"end":{"line":98,"column":1}},"key":"kcrndVzT6D"}],"urlSource":"https://2023.ieeeigarss.org/view_paper.php?PaperNum=5306","key":"eBaC3mHbmH"}],"key":"yrvMFPd0Eh"}],"key":"DiDSQ7yUBp"},{"type":"listItem","spread":true,"position":{"start":{"line":99,"column":1},"end":{"line":99,"column":1}},"children":[{"type":"paragraph","children":[{"type":"text","value":"ESIP Talk on Cloud Native Formats: ","position":{"start":{"line":99,"column":1},"end":{"line":99,"column":1}},"key":"U30Nsg6Dwo"},{"type":"link","url":"https://www.youtube.com/watch?v=ac_UKunUrNM","position":{"start":{"line":99,"column":1},"end":{"line":99,"column":1}},"children":[{"type":"text","value":"https://​www​.youtube​.com​/watch​?v​=​ac​_UKunUrNM","position":{"start":{"line":99,"column":1},"end":{"line":99,"column":1}},"key":"ugYCQ3r9C8"}],"urlSource":"https://www.youtube.com/watch?v=ac_UKunUrNM","key":"jstmWEaZ6U"}],"key":"rcF5Kb23wP"}],"key":"HWTnnqETDw"},{"type":"listItem","spread":true,"position":{"start":{"line":100,"column":1},"end":{"line":102,"column":1}},"children":[{"type":"paragraph","children":[{"type":"text","value":"FOSS4G Talk On Cloud Native Formats (Matthew Hanson)","position":{"start":{"line":100,"column":1},"end":{"line":100,"column":1}},"key":"aOzFlQofZD"}],"key":"FUIU6Rh7aP"},{"type":"list","ordered":false,"spread":false,"position":{"start":{"line":101,"column":1},"end":{"line":102,"column":1}},"children":[{"type":"listItem","spread":true,"position":{"start":{"line":101,"column":1},"end":{"line":101,"column":1}},"children":[{"type":"paragraph","children":[{"type":"link","url":"https://talks.osgeo.org/foss4g-2023/talk/XBHYF9/","position":{"start":{"line":101,"column":1},"end":{"line":101,"column":1}},"children":[{"type":"text","value":"https://​talks​.osgeo​.org​/foss4g​-2023​/talk​/XBHYF9/","position":{"start":{"line":101,"column":1},"end":{"line":101,"column":1}},"key":"NN59aja1OM"}],"urlSource":"https://talks.osgeo.org/foss4g-2023/talk/XBHYF9/","key":"o26Bb3p5Ch"}],"key":"eDGg388EQl"}],"key":"NC0uSsHUQl"},{"type":"listItem","spread":true,"position":{"start":{"line":102,"column":1},"end":{"line":102,"column":1}},"children":[{"type":"paragraph","children":[{"type":"link","url":"https://youtu.be/g7iMO1KmyJE?si=erNwG1VzwUIQR3t5","position":{"start":{"line":102,"column":1},"end":{"line":102,"column":1}},"children":[{"type":"text","value":"https://​youtu​.be​/g7iMO1KmyJE​?si​=​erNwG1VzwUIQR3t5","position":{"start":{"line":102,"column":1},"end":{"line":102,"column":1}},"key":"NQ7JJBro4R"}],"urlSource":"https://youtu.be/g7iMO1KmyJE?si=erNwG1VzwUIQR3t5","key":"LLUPeQI2X6"}],"key":"fSsp4bO7sw"}],"key":"AbBxM6xBP8"}],"key":"Sas228Oq5A"}],"key":"JuxUkMZerz"},{"type":"listItem","spread":true,"position":{"start":{"line":103,"column":1},"end":{"line":106,"column":1}},"children":[{"type":"paragraph","children":[{"type":"text","value":"OGC White Paper on Cloud Native Formats (Chris Holmes, Scott Simmons):","position":{"start":{"line":103,"column":1},"end":{"line":103,"column":1}},"key":"YoWjnvg3IR"}],"key":"Pw9d5NRx9j"},{"type":"list","ordered":false,"spread":false,"position":{"start":{"line":104,"column":1},"end":{"line":106,"column":1}},"children":[{"type":"listItem","spread":true,"position":{"start":{"line":104,"column":1},"end":{"line":104,"column":1}},"children":[{"type":"paragraph","children":[{"type":"link","url":"https://www.ogc.org/blog-article/towards-a-cloud-native-ogc/","position":{"start":{"line":104,"column":1},"end":{"line":104,"column":1}},"children":[{"type":"text","value":"https://​www​.ogc​.org​/blog​-article​/towards​-a​-cloud​-native​-ogc/","position":{"start":{"line":104,"column":1},"end":{"line":104,"column":1}},"key":"to4PRZj1O2"}],"urlSource":"https://www.ogc.org/blog-article/towards-a-cloud-native-ogc/","key":"AHvz73cUX3"}],"key":"EqU09vw8q9"}],"key":"dqOqq081oV"},{"type":"listItem","spread":true,"position":{"start":{"line":105,"column":1},"end":{"line":105,"column":1}},"children":[{"type":"paragraph","children":[{"type":"link","url":"https://www.ogc.org/blog-article/towards-a-cloud-native-geospatial-standards-baseline/","position":{"start":{"line":105,"column":1},"end":{"line":105,"column":1}},"children":[{"type":"text","value":"https://​www​.ogc​.org​/blog​-article​/towards​-a​-cloud​-native​-geospatial​-standards​-baseline/","position":{"start":{"line":105,"column":1},"end":{"line":105,"column":1}},"key":"lSUxzl4efn"}],"urlSource":"https://www.ogc.org/blog-article/towards-a-cloud-native-geospatial-standards-baseline/","key":"GhCWLovzZE"}],"key":"nRBVTa7IBx"}],"key":"JFCZBnKLnn"},{"type":"listItem","spread":true,"position":{"start":{"line":106,"column":1},"end":{"line":106,"column":1}},"children":[{"type":"paragraph","children":[{"type":"link","url":"https://www.ogc.org/blog-article/the-latest-on-cloud-native-geospatial-standards-in-ogc/","position":{"start":{"line":106,"column":1},"end":{"line":106,"column":1}},"children":[{"type":"text","value":"https://​www​.ogc​.org​/blog​-article​/the​-latest​-on​-cloud​-native​-geospatial​-standards​-in​-ogc/","position":{"start":{"line":106,"column":1},"end":{"line":106,"column":1}},"key":"oCMTj5JBXh"}],"urlSource":"https://www.ogc.org/blog-article/the-latest-on-cloud-native-geospatial-standards-in-ogc/","key":"neGTpd5uoL"}],"key":"tTR0x39W0N"}],"key":"UmnLPb7G6b"}],"key":"kNZ8oz1kKE"}],"key":"szXhnjQaVx"},{"type":"listItem","spread":true,"position":{"start":{"line":107,"column":1},"end":{"line":109,"column":1}},"children":[{"type":"paragraph","children":[{"type":"text","value":"Cloud-Native Geospatial Foundation initiative of Radiant Earth:","position":{"start":{"line":107,"column":1},"end":{"line":107,"column":1}},"key":"cSXslVgDWG"}],"key":"xyWONV1Dju"},{"type":"list","ordered":false,"spread":false,"position":{"start":{"line":108,"column":1},"end":{"line":109,"column":1}},"children":[{"type":"listItem","spread":true,"position":{"start":{"line":108,"column":1},"end":{"line":109,"column":1}},"children":[{"type":"paragraph","children":[{"type":"link","url":"https://cloudnativegeo.org","position":{"start":{"line":108,"column":1},"end":{"line":108,"column":1}},"children":[{"type":"text","value":"https://​cloudnativegeo​.org","position":{"start":{"line":108,"column":1},"end":{"line":108,"column":1}},"key":"AXG0qbqJnH"}],"urlSource":"https://cloudnativegeo.org","key":"HIpbukPG5o"}],"key":"zvU0rr8LaR"}],"key":"YPghJpAKu7"}],"key":"xxYutxr6S9"}],"key":"yn7CVuZJbw"}],"key":"PjoHQYSqmV"},{"type":"heading","depth":2,"position":{"start":{"line":110,"column":1},"end":{"line":110,"column":1}},"children":[{"type":"text","value":"Scaling","position":{"start":{"line":110,"column":1},"end":{"line":110,"column":1}},"key":"ohlOyyo2f1"}],"identifier":"scaling","label":"Scaling","html_id":"scaling","implicit":true,"key":"LwYJ9tYnpb"},{"type":"paragraph","position":{"start":{"line":112,"column":1},"end":{"line":112,"column":1}},"children":[{"type":"text","value":"Scaling refers to the process of increasing or decreasing the capacity or size of a system to handle a larger or smaller workload or data volume. Scaling does not necessarily means only in the direction of larger and bigger but also saving unnecessary costs in times when there is no traffic. In our context, scaling involves managing the growth of data, traffic, or processing requirements to ensure optimal performance and availability.","position":{"start":{"line":112,"column":1},"end":{"line":112,"column":1}},"key":"pxA46PceWT"}],"key":"Ur3aMYJrpy"},{"type":"heading","depth":3,"position":{"start":{"line":114,"column":1},"end":{"line":114,"column":1}},"children":[{"type":"text","value":"Horizontal vs vertical scaling","position":{"start":{"line":114,"column":1},"end":{"line":114,"column":1}},"key":"kJtc9W22aj"}],"identifier":"horizontal-vs-vertical-scaling","label":"Horizontal vs vertical scaling","html_id":"horizontal-vs-vertical-scaling","implicit":true,"key":"AcqG8MpmQ6"},{"type":"paragraph","position":{"start":{"line":116,"column":1},"end":{"line":116,"column":1}},"children":[{"type":"text","value":"Two classical approaches to scaling are horizontal and vertical:","position":{"start":{"line":116,"column":1},"end":{"line":116,"column":1}},"key":"ag5QUBVQEJ"}],"key":"gJ13naIIoq"},{"type":"list","ordered":false,"spread":false,"position":{"start":{"line":118,"column":1},"end":{"line":120,"column":1}},"children":[{"type":"listItem","spread":true,"position":{"start":{"line":118,"column":1},"end":{"line":118,"column":1}},"children":[{"type":"paragraph","children":[{"type":"strong","position":{"start":{"line":118,"column":1},"end":{"line":118,"column":1}},"children":[{"type":"text","value":"Horizontal scaling:","position":{"start":{"line":118,"column":1},"end":{"line":118,"column":1}},"key":"tBd4nNqASF"}],"key":"uNnVJNJUvk"},{"type":"text","value":" Also known as scaling out, horizontal scaling involves adding more machines or nodes to distribute the workload across a larger number of resources. This could mean adding more servers or instances to handle increased traffic or data processing demands. Horizontal scaling offers the advantage of improved fault tolerance and increased capacity, as the workload is spread across multiple resources.","position":{"start":{"line":118,"column":1},"end":{"line":118,"column":1}},"key":"LV4kZWJPsB"}],"key":"l1ucgFcIie"}],"key":"JmdyYGyl5j"},{"type":"listItem","spread":true,"position":{"start":{"line":119,"column":1},"end":{"line":120,"column":1}},"children":[{"type":"paragraph","children":[{"type":"strong","position":{"start":{"line":119,"column":1},"end":{"line":119,"column":1}},"children":[{"type":"text","value":"Vertical scaling:","position":{"start":{"line":119,"column":1},"end":{"line":119,"column":1}},"key":"hYsfPv7G7X"}],"key":"QO2ryYUJT3"},{"type":"text","value":" Also known as scaling up, vertical scaling involves increasing the capacity of an individual machine or resource. This can be achieved by upgrading the hardware, such as adding more powerful processors, memory, or storage, to handle the growing demands of the geospatial application. Vertical scaling is often suitable for applications with single-node architectures or when the workload cannot be easily distributed across multiple machines.","position":{"start":{"line":119,"column":1},"end":{"line":119,"column":1}},"key":"TysrWAPXoT"}],"key":"CPSxYsm2qo"}],"key":"MtDPT0xnq1"}],"key":"HFbApPDYgA"},{"type":"paragraph","position":{"start":{"line":121,"column":1},"end":{"line":121,"column":1}},"children":[{"type":"text","value":"Both horizontal and vertical scaling have their advantages and considerations. Horizontal scaling provides better scalability and fault tolerance, as it can handle increased traffic and processing by adding more resources. However, it may require additional effort to distribute and synchronize data across multiple nodes. Vertical scaling, on the other hand, simplifies data management as all resources are contained within a single node, but it may have limitations in terms of the maximum capacity a single machine can handle.","position":{"start":{"line":121,"column":1},"end":{"line":121,"column":1}},"key":"UYf84KRKHf"}],"key":"NmIpirHFn8"},{"type":"paragraph","position":{"start":{"line":123,"column":1},"end":{"line":123,"column":1}},"children":[{"type":"text","value":"In common workflows, a combination of both approaches is used to ensure optimal speed and resource utilization while being able to keep the simplicity of a workflow.","position":{"start":{"line":123,"column":1},"end":{"line":123,"column":1}},"key":"yZ2ft0hk28"}],"key":"vxQXKWWF2W"},{"type":"heading","depth":3,"position":{"start":{"line":125,"column":1},"end":{"line":125,"column":1}},"children":[{"type":"text","value":"How to scale","position":{"start":{"line":125,"column":1},"end":{"line":125,"column":1}},"key":"LzvtYzgEha"}],"identifier":"how-to-scale","label":"How to scale","html_id":"how-to-scale","implicit":true,"key":"CTkHp6VTKb"},{"type":"paragraph","position":{"start":{"line":127,"column":1},"end":{"line":127,"column":1}},"children":[{"type":"text","value":"There are many approaches how to handle scaling properly and we will use two excercises to experiment ","position":{"start":{"line":127,"column":1},"end":{"line":127,"column":1}},"key":"OpPURAcAEZ"},{"type":"strong","position":{"start":{"line":127,"column":1},"end":{"line":127,"column":1}},"children":[{"type":"text","value":"Vertical scaling","position":{"start":{"line":127,"column":1},"end":{"line":127,"column":1}},"key":"hRHdU26fC3"}],"key":"HQ8fcST5cO"},{"type":"text","value":" and ","position":{"start":{"line":127,"column":1},"end":{"line":127,"column":1}},"key":"eiCIAffq7E"},{"type":"strong","position":{"start":{"line":127,"column":1},"end":{"line":127,"column":1}},"children":[{"type":"text","value":"Horizontal scaling","position":{"start":{"line":127,"column":1},"end":{"line":127,"column":1}},"key":"tFJF0Hf3Qz"}],"key":"fFjhWnFAAg"},{"type":"text","value":" using the Dask library, together with chunking strategies.","position":{"start":{"line":127,"column":1},"end":{"line":127,"column":1}},"key":"pM1TuOe7of"}],"key":"f4mNThf0RS"},{"type":"paragraph","position":{"start":{"line":129,"column":1},"end":{"line":129,"column":1}},"children":[{"type":"link","url":"https://github.com/EO-College/cubes-and-clouds/blob/main/lectures/2.4_formats_and_performance/exercises/24_chunking.ipynb","position":{"start":{"line":129,"column":1},"end":{"line":129,"column":1}},"children":[{"type":"text","value":"Exercise 2.4 chunking","position":{"start":{"line":129,"column":1},"end":{"line":129,"column":1}},"key":"a7ZuHSoeYu"}],"urlSource":"https://github.com/EO-College/cubes-and-clouds/blob/main/lectures/2.4_formats_and_performance/exercises/24_chunking.ipynb","data":{"kind":"file","org":"EO-College","repo":"cubes-and-clouds","reference":"main","file":"lectures/2.4_formats_and_performance/exercises/24_chunking.ipynb","raw":"https://raw.githubusercontent.com/EO-College/cubes-and-clouds/main/lectures/2.4_formats_and_performance/exercises/24_chunking.ipynb"},"internal":false,"protocol":"github","key":"PCMQteqC14"}],"key":"U8Jtjo3pUp"},{"type":"paragraph","position":{"start":{"line":131,"column":1},"end":{"line":131,"column":1}},"children":[{"type":"link","url":"https://github.com/EO-College/cubes-and-clouds/blob/main/lectures/2.4_formats_and_performance/exercises/24_dask.ipynb","position":{"start":{"line":131,"column":1},"end":{"line":131,"column":1}},"children":[{"type":"text","value":"Exercise 2.4 dask","position":{"start":{"line":131,"column":1},"end":{"line":131,"column":1}},"key":"ULsEAC2W2Y"}],"urlSource":"https://github.com/EO-College/cubes-and-clouds/blob/main/lectures/2.4_formats_and_performance/exercises/24_dask.ipynb","data":{"kind":"file","org":"EO-College","repo":"cubes-and-clouds","reference":"main","file":"lectures/2.4_formats_and_performance/exercises/24_dask.ipynb","raw":"https://raw.githubusercontent.com/EO-College/cubes-and-clouds/main/lectures/2.4_formats_and_performance/exercises/24_dask.ipynb"},"internal":false,"protocol":"github","key":"TVViKT1IUB"}],"key":"oi6JY92LKN"},{"type":"heading","depth":3,"position":{"start":{"line":133,"column":1},"end":{"line":133,"column":1}},"children":[{"type":"text","value":"Cost of scalability","position":{"start":{"line":133,"column":1},"end":{"line":133,"column":1}},"key":"REeE7Rgvx5"}],"identifier":"cost-of-scalability","label":"Cost of scalability","html_id":"cost-of-scalability","implicit":true,"key":"q1LTp86LLO"},{"type":"paragraph","position":{"start":{"line":135,"column":1},"end":{"line":135,"column":1}},"children":[{"type":"text","value":"Executing code, whether on your own computer or a cloud platform, comes with costs—both financial and environmental. Every computation step consumes resources and energy. While simple computations like sorting a small list are quick and resource-light, more complex workflows, such as training a machine learning model or processing large datasets, can be resource-intensive.","position":{"start":{"line":135,"column":1},"end":{"line":135,"column":1}},"key":"hjbGBNVPep"}],"key":"HsyYpLtEDj"},{"type":"paragraph","position":{"start":{"line":137,"column":1},"end":{"line":137,"column":1}},"children":[{"type":"text","value":"These resource-intensive workflows not only require significant energy but also take considerable time. Saving just a few seconds in a small workflow might seem insignificant, but in large-scale computations, those seconds can translate into hours or even days saved.","position":{"start":{"line":137,"column":1},"end":{"line":137,"column":1}},"key":"KfHwN9Yl47"}],"key":"x3GAQ5cZj2"},{"type":"paragraph","position":{"start":{"line":139,"column":1},"end":{"line":140,"column":1}},"children":[{"type":"text","value":"It’s important to measure and understand the resource consumption of your workflows to minimize their environmental impact. Tools like ","position":{"start":{"line":139,"column":1},"end":{"line":139,"column":1}},"key":"TIWEwljTi0"},{"type":"inlineCode","value":"Codecarbon","position":{"start":{"line":139,"column":1},"end":{"line":139,"column":1}},"key":"k2CKE8DDRz"},{"type":"text","value":" can estimate the energy use of your code, providing a starting point for optimization. You can read more about the tool ","position":{"start":{"line":139,"column":1},"end":{"line":139,"column":1}},"key":"biCiYe84x0"},{"type":"link","url":"https://codecarbon.io/","position":{"start":{"line":139,"column":1},"end":{"line":139,"column":1}},"children":[{"type":"text","value":"online","position":{"start":{"line":139,"column":1},"end":{"line":139,"column":1}},"key":"AjsRiYRtpX"}],"urlSource":"https://codecarbon.io/","key":"hDSMC8PtCt"},{"type":"text","value":" or on ","position":{"start":{"line":139,"column":1},"end":{"line":139,"column":1}},"key":"hGSwQDfOUD"},{"type":"link","url":"https://github.com/mlco2/codecarbon","position":{"start":{"line":139,"column":1},"end":{"line":139,"column":1}},"children":[{"type":"text","value":"GitHub","position":{"start":{"line":139,"column":1},"end":{"line":139,"column":1}},"key":"l3ByxzOplt"}],"urlSource":"https://github.com/mlco2/codecarbon","error":true,"key":"OV8g0whK1U"},{"type":"text","value":".\nNo tool is perfect, so interpreting results critically and understanding their limitations is essential. However, using such tools can help raise awareness and guide improvements.","position":{"start":{"line":139,"column":1},"end":{"line":139,"column":1}},"key":"bGZvRhsZc1"}],"key":"MB9hO7el2x"},{"type":"paragraph","position":{"start":{"line":142,"column":1},"end":{"line":142,"column":1}},"children":[{"type":"text","value":"On cloud platforms, optimizing resource usage doesn’t just reduce your carbon footprint—it can also save you money.","position":{"start":{"line":142,"column":1},"end":{"line":142,"column":1}},"key":"VGz0gLGvV8"}],"key":"q9MxeleACu"},{"type":"paragraph","position":{"start":{"line":144,"column":1},"end":{"line":144,"column":1}},"children":[{"type":"text","value":"As you design and execute workflows, think about how you can reduce complexity, reuse existing resources, and streamline processes. By doing so, you’re contributing to a more sustainable approach to computing.","position":{"start":{"line":144,"column":1},"end":{"line":144,"column":1}},"key":"xTmgcvFkuE"}],"key":"Ut0xfoI403"},{"type":"paragraph","position":{"start":{"line":146,"column":1},"end":{"line":146,"column":1}},"children":[{"type":"text","value":"Try now to measure the energy footprint of your workflow in the following exercise!","position":{"start":{"line":146,"column":1},"end":{"line":146,"column":1}},"key":"xQx108Sq18"}],"key":"Gw6KbAAfO9"},{"type":"paragraph","position":{"start":{"line":148,"column":1},"end":{"line":148,"column":1}},"children":[{"type":"link","url":"https://github.com/EO-College/cubes-and-clouds/blob/main/lectures/2.4_formats_and_performance/exercises/24_energy_consumption.ipynb","position":{"start":{"line":148,"column":1},"end":{"line":148,"column":1}},"children":[{"type":"text","value":"Exercise 2.4 Formats and Performance","position":{"start":{"line":148,"column":1},"end":{"line":148,"column":1}},"key":"gsvxDw1GqP"}],"urlSource":"https://github.com/EO-College/cubes-and-clouds/blob/main/lectures/2.4_formats_and_performance/exercises/24_energy_consumption.ipynb","data":{"kind":"file","org":"EO-College","repo":"cubes-and-clouds","reference":"main","file":"lectures/2.4_formats_and_performance/exercises/24_energy_consumption.ipynb","raw":"https://raw.githubusercontent.com/EO-College/cubes-and-clouds/main/lectures/2.4_formats_and_performance/exercises/24_energy_consumption.ipynb"},"internal":false,"protocol":"github","key":"Efm0DCVZGp"}],"key":"mEXYTS24Zf"},{"type":"heading","depth":3,"position":{"start":{"line":150,"column":1},"end":{"line":150,"column":1}},"children":[{"type":"text","value":"Subscription vs. On-Demand usage","position":{"start":{"line":150,"column":1},"end":{"line":150,"column":1}},"key":"I5yHZTIKri"}],"identifier":"subscription-vs-on-demand-usage","label":"Subscription vs. On-Demand usage","html_id":"subscription-vs-on-demand-usage","implicit":true,"key":"Yj7VyunWd5"},{"type":"paragraph","position":{"start":{"line":152,"column":1},"end":{"line":152,"column":1}},"children":[{"type":"strong","position":{"start":{"line":152,"column":1},"end":{"line":152,"column":1}},"children":[{"type":"text","value":"Subscription:","position":{"start":{"line":152,"column":1},"end":{"line":152,"column":1}},"key":"zciWZvXoJW"}],"key":"vFHXs1csJQ"},{"type":"text","value":" A subscription model involves a fixed, recurring payment made by the user to access and utilize the cloud platform’s services over a specific period, typically monthly or annually. Under a subscription model, users typically commit to a predetermined level of resources and pay a regular fee regardless of the actual usage during that period. This model often provides cost predictability and may offer discounts or benefits for long-term commitments. Users can usually choose from various options and combinations of resources (eg. GPU, CPU, disk storage combinations).","position":{"start":{"line":152,"column":1},"end":{"line":152,"column":1}},"key":"pIiuELLPcD"}],"key":"cMIH6f3CWf"},{"type":"paragraph","position":{"start":{"line":154,"column":1},"end":{"line":154,"column":1}},"children":[{"type":"text","value":"Advantages of the Subscription Model:","position":{"start":{"line":154,"column":1},"end":{"line":154,"column":1}},"key":"a2Fv1lQOAg"}],"key":"SiNhtEklSs"},{"type":"list","ordered":false,"spread":false,"position":{"start":{"line":156,"column":1},"end":{"line":159,"column":1}},"children":[{"type":"listItem","spread":true,"position":{"start":{"line":156,"column":1},"end":{"line":156,"column":1}},"children":[{"type":"paragraph","children":[{"type":"text","value":"Cost Predictability: Users have a clear understanding of the ongoing costs as they pay a fixed fee.","position":{"start":{"line":156,"column":1},"end":{"line":156,"column":1}},"key":"hTClW6r9cy"}],"key":"mUPTXCDb4I"}],"key":"FIgIzzoo4Y"},{"type":"listItem","spread":true,"position":{"start":{"line":157,"column":1},"end":{"line":157,"column":1}},"children":[{"type":"paragraph","children":[{"type":"text","value":"Potential Cost Savings: Subscriptions may offer discounts or cost benefits for longer-term commitments.","position":{"start":{"line":157,"column":1},"end":{"line":157,"column":1}},"key":"aIHYoBPGMA"}],"key":"v34A3xrp0E"}],"key":"gVi1SVfBYv"},{"type":"listItem","spread":true,"position":{"start":{"line":158,"column":1},"end":{"line":159,"column":1}},"children":[{"type":"paragraph","children":[{"type":"text","value":"Continuous Service Access: Users have continuous access to the subscribed services without the need for frequent renewal or payment management.","position":{"start":{"line":158,"column":1},"end":{"line":158,"column":1}},"key":"RtJAoFBdFx"}],"key":"rpR3CnEMGp"}],"key":"mWIpVu3Ez5"}],"key":"NNAVl7uYq5"},{"type":"paragraph","position":{"start":{"line":160,"column":1},"end":{"line":160,"column":1}},"children":[{"type":"strong","position":{"start":{"line":160,"column":1},"end":{"line":160,"column":1}},"children":[{"type":"text","value":"On-Demand Usage:","position":{"start":{"line":160,"column":1},"end":{"line":160,"column":1}},"key":"r5bWm2NZPK"}],"key":"KLoAumDSLQ"},{"type":"text","value":" In an on-demand model, users pay for the cloud platform’s services based on actual usage and consumption. Users are charged on a pay-as-you-go basis, where they pay for the resources or services they utilize in a given period. There are no long-term commitments or fixed fees. This model offers flexibility and scalability, allowing users to scale resources up or down as per their needs.","position":{"start":{"line":160,"column":1},"end":{"line":160,"column":1}},"key":"cQD0rbjVEw"}],"key":"FR9rL5XstG"},{"type":"paragraph","position":{"start":{"line":162,"column":1},"end":{"line":162,"column":1}},"children":[{"type":"text","value":"Advantages of On-Demand Usage:","position":{"start":{"line":162,"column":1},"end":{"line":162,"column":1}},"key":"bEI46RqQMf"}],"key":"GXwzWv0tOr"},{"type":"list","ordered":false,"spread":false,"position":{"start":{"line":164,"column":1},"end":{"line":167,"column":1}},"children":[{"type":"listItem","spread":true,"position":{"start":{"line":164,"column":1},"end":{"line":164,"column":1}},"children":[{"type":"paragraph","children":[{"type":"text","value":"Flexibility: Users have the flexibility to adjust resources based on their varying demands, scaling up or down as required.","position":{"start":{"line":164,"column":1},"end":{"line":164,"column":1}},"key":"akkABp9aTa"}],"key":"l7L6lPuyTb"}],"key":"ElyjS6G269"},{"type":"listItem","spread":true,"position":{"start":{"line":165,"column":1},"end":{"line":165,"column":1}},"children":[{"type":"paragraph","children":[{"type":"text","value":"Cost Efficiency: Users only pay for what they use, making it suitable for workloads with unpredictable or fluctuating resource needs.","position":{"start":{"line":165,"column":1},"end":{"line":165,"column":1}},"key":"J7GryI9mpw"}],"key":"i0RU03t1IK"}],"key":"XhS3dsSBZ2"},{"type":"listItem","spread":true,"position":{"start":{"line":166,"column":1},"end":{"line":167,"column":1}},"children":[{"type":"paragraph","children":[{"type":"text","value":"No Long-Term Commitments: On-demand models do not require users to commit to a specific period or predefined resource levels, allowing for agility and quick adjustments.","position":{"start":{"line":166,"column":1},"end":{"line":166,"column":1}},"key":"Hxiap2poy4"}],"key":"BQanDbmkCY"}],"key":"sQmNYTcIgl"}],"key":"XrWe7QwkNd"},{"type":"paragraph","position":{"start":{"line":168,"column":1},"end":{"line":168,"column":1}},"children":[{"type":"text","value":"Choosing between subscription and on-demand models depends on various factors, including the nature of your workloads, budget considerations, and usage patterns. Based on this (and data availability) users can choose a platform that suits their needs best. Reviewing the pricing details is an important part before selecting a working environment.","position":{"start":{"line":168,"column":1},"end":{"line":168,"column":1}},"key":"CnqjMwkyHO"}],"key":"PaD4pmwDbM"},{"type":"heading","depth":3,"position":{"start":{"line":170,"column":1},"end":{"line":170,"column":1}},"children":[{"type":"text","value":"References","position":{"start":{"line":170,"column":1},"end":{"line":170,"column":1}},"key":"mo9OHYWk6u"}],"identifier":"references","label":"References","html_id":"references","implicit":true,"key":"Tdcy4q53L8"},{"type":"list","ordered":false,"spread":false,"position":{"start":{"line":171,"column":1},"end":{"line":174,"column":1}},"children":[{"type":"listItem","spread":true,"position":{"start":{"line":171,"column":1},"end":{"line":171,"column":1}},"children":[{"type":"paragraph","children":[{"type":"link","url":"https://mlco2.github.io/codecarbon/","position":{"start":{"line":171,"column":1},"end":{"line":171,"column":1}},"children":[{"type":"text","value":"codecarbon (2024)","position":{"start":{"line":171,"column":1},"end":{"line":171,"column":1}},"key":"Rjm4HAHUGC"}],"urlSource":"https://mlco2.github.io/codecarbon/","key":"xmsZ6pejuN"},{"type":"text","value":"; Reference: Courty, B., Schmidt, V., Goyal-Kamal, MarionCoutarel, Feld, B., Lecourt, J., LiamConnell, SabAmine, Inimaz, Supatomic, Léval, M., Blanche, L., Cruveiller, A., Ouminasara, Zhao, F., Joshi, A., Bogroff, A., Saboni, A., De Lavoreille, H., . . . MinervaBooks. (2024). mlco2/codecarbon: v2.4.1. Zenodo. ","position":{"start":{"line":171,"column":1},"end":{"line":171,"column":1}},"key":"HnqUSjYpvK"},{"type":"cite","url":"https://doi.org/10.5281/zenodo.11171501","position":{"start":{"line":171,"column":1},"end":{"line":171,"column":1}},"children":[{"type":"text","value":"DOI: https://doi.org/10.5281/zenodo.11171501","position":{"start":{"line":171,"column":1},"end":{"line":171,"column":1}},"key":"mGpRZHbrDX"}],"kind":"narrative","label":"https://doi.org/10.5281/zenodo.11171501","identifier":"https://doi.org/10.5281/zenodo.11171501","enumerator":"1","key":"Tazk6lQEC1"}],"key":"ayDz8FUHAt"}],"key":"NxQ47pfzSE"},{"type":"listItem","spread":true,"position":{"start":{"line":172,"column":1},"end":{"line":174,"column":1}},"children":[{"type":"paragraph","children":[{"type":"text","value":"Dask Development Team (2016). Dask: Library for dynamic task scheduling\nURL ","position":{"start":{"line":172,"column":1},"end":{"line":172,"column":1}},"key":"t47EGzsTkd"},{"type":"link","url":"http://dask.pydata.org","position":{"start":{"line":172,"column":1},"end":{"line":172,"column":1}},"children":[{"type":"text","value":"http://​dask​.pydata​.org","position":{"start":{"line":172,"column":1},"end":{"line":172,"column":1}},"key":"Wyi8t8JWPi"}],"urlSource":"http://dask.pydata.org","key":"uSrve5j2HY"}],"key":"NErBijmhSB"}],"key":"TTQk9FliFd"}],"key":"MKBPnbR0kM"},{"type":"heading","depth":2,"position":{"start":{"line":175,"column":1},"end":{"line":175,"column":1}},"children":[{"type":"text","value":"What to avoid and what are the limitations","position":{"start":{"line":175,"column":1},"end":{"line":175,"column":1}},"key":"q5gJ3iEt64"}],"identifier":"what-to-avoid-and-what-are-the-limitations","label":"What to avoid and what are the limitations","html_id":"what-to-avoid-and-what-are-the-limitations","implicit":true,"key":"fAm9oBensH"},{"type":"paragraph","position":{"start":{"line":177,"column":1},"end":{"line":177,"column":1}},"children":[{"type":"text","value":"While scaling is providing many options and is essential for achieving results on a larger scale, there are some limitations to keep in mind and activities to even avoid.","position":{"start":{"line":177,"column":1},"end":{"line":177,"column":1}},"key":"Hq745tjtuN"}],"key":"IxNkASybwO"},{"type":"paragraph","position":{"start":{"line":179,"column":1},"end":{"line":179,"column":1}},"children":[{"type":"strong","position":{"start":{"line":179,"column":1},"end":{"line":179,"column":1}},"children":[{"type":"text","value":"Costs","position":{"start":{"line":179,"column":1},"end":{"line":179,"column":1}},"key":"eYIYbr93Hi"}],"key":"Tq8x69Du6a"},{"type":"text","value":": One of the main characteristics to consider are costs of computing. Scaling resources dynamically can lead to increased costs, especially if not properly managed. It is essential to monitor resource usage and set appropriate maximum scaling policies to ensure cost optimization. Failure to do so may result in unnecessary provisioning of resources, leading to higher expenses. The purchase of many computational resources can be easy, but very costly. Code optimization is important to ensure there are no memory leaks, unnecessary data storage, and other expensive operations.","position":{"start":{"line":179,"column":1},"end":{"line":179,"column":1}},"key":"CeTO2CwvwE"}],"key":"zC1KRpX20y"},{"type":"paragraph","position":{"start":{"line":181,"column":1},"end":{"line":181,"column":1}},"children":[{"type":"strong","position":{"start":{"line":181,"column":1},"end":{"line":181,"column":1}},"children":[{"type":"text","value":"Data Access","position":{"start":{"line":181,"column":1},"end":{"line":181,"column":1}},"key":"oDublGNW4Q"}],"key":"beAR3ozRoR"},{"type":"text","value":": In geospatial cloud workflows, one of the big challenges lies in data access and optimal data storage. The easy trap is in loading large portions of unnecessary data without applying correct filters ahead. Such data volumes can lead to more requirements on RAM or disk space resulting in higher costs of processing or longer times (and more computational time) just to load the data.","position":{"start":{"line":181,"column":1},"end":{"line":181,"column":1}},"key":"CSEzBvFxat"}],"key":"CzT3Tn1Lve"},{"type":"paragraph","position":{"start":{"line":183,"column":1},"end":{"line":183,"column":1}},"children":[{"type":"strong","position":{"start":{"line":183,"column":1},"end":{"line":183,"column":1}},"children":[{"type":"text","value":"Accessing data as files","position":{"start":{"line":183,"column":1},"end":{"line":183,"column":1}},"key":"b7a5gRxQhP"}],"key":"mmiOoGggqI"},{"type":"text","value":": Geospatial data are stored in many formats as discussed in this lesson and some are more appropriate to access in the cloud. The opportunity of first evaluating metadata before loading the whole dataset is great for saving time and money.","position":{"start":{"line":183,"column":1},"end":{"line":183,"column":1}},"key":"baiJVeQzFr"}],"key":"BQyYjOZ5bZ"},{"type":"paragraph","position":{"start":{"line":185,"column":1},"end":{"line":185,"column":1}},"children":[{"type":"strong","position":{"start":{"line":185,"column":1},"end":{"line":185,"column":1}},"children":[{"type":"text","value":"Latency and Data Transfer","position":{"start":{"line":185,"column":1},"end":{"line":185,"column":1}},"key":"egqX8B3faf"}],"key":"YRCvPKS1Xp"},{"type":"text","value":": In distributed and scaled-out architectures, managing data transfer and minimizing latency can be crucial. Moving data between services or instances across different locations can introduce network overhead and impact application performance. Efficient data caching, or data partitioning strategies can help mitigate these challenges.","position":{"start":{"line":185,"column":1},"end":{"line":185,"column":1}},"key":"YNHpmukv3j"}],"key":"NmGOl1dAB0"},{"type":"paragraph","position":{"start":{"line":187,"column":1},"end":{"line":187,"column":1}},"children":[{"type":"strong","position":{"start":{"line":187,"column":1},"end":{"line":187,"column":1}},"children":[{"type":"text","value":"Scaling Limits in the platform","position":{"start":{"line":187,"column":1},"end":{"line":187,"column":1}},"key":"uuWGU6GYV6"}],"key":"U0xU5T3elc"},{"type":"text","value":": While cloud platforms offer high scalability, there are still practical limits to consider. Every service or resource has its scalability limits, such as maximum instance count, storage capacity, or network throughput. It is important to understand these limitations and design your programs and applications accordingly.","position":{"start":{"line":187,"column":1},"end":{"line":187,"column":1}},"key":"B7wEF9YKcU"}],"key":"vx1Wa4AoHq"},{"type":"paragraph","position":{"start":{"line":189,"column":1},"end":{"line":189,"column":1}},"children":[{"type":"text","value":"To mitigate these challenges and limitations, it’s advisable to thoroughly plan and architect your application for scalability, leverage cloud-native tools and services, monitor resource usage and costs, and regularly test and optimize your scaling strategies. Additionally, staying updated with the latest advancements in cloud technologies and best practices will help you navigate the complexities of cloud-native scaling more effectively.","position":{"start":{"line":189,"column":1},"end":{"line":189,"column":1}},"key":"EBa4q6zYOC"}],"key":"UYBPZPYTZB"},{"type":"heading","depth":2,"position":{"start":{"line":191,"column":1},"end":{"line":191,"column":1}},"children":[{"type":"text","value":"Quiz","position":{"start":{"line":191,"column":1},"end":{"line":191,"column":1}},"key":"BWJ0PP6ye6"}],"identifier":"quiz","label":"Quiz","html_id":"quiz","implicit":true,"key":"mn9RApNg04"},{"type":"paragraph","position":{"start":{"line":193,"column":1},"end":{"line":193,"column":1}},"children":[{"type":"text","value":"What are cloud native data formats in EO and GIS","position":{"start":{"line":193,"column":1},"end":{"line":193,"column":1}},"key":"KRDBLAgko7"}],"key":"EGQDo7xxly"},{"type":"code","lang":"","value":"[(X)] Cloud native data formats in EO should be compatible to cloud services (APIs, http requests, cloud storage), enable fast viewing and access to spatial sub regions.\n[( )] Cloud native data formats in EO are exclusively designed to be compressed as much as possible, so that the least amount of storage space is necessary.\n[( )] Cloud native data formats in EO have to be human readable when you open them in a text editor.","position":{"start":{"line":195,"column":1},"end":{"line":197,"column":1}},"key":"iXFvPZ50BP"},{"type":"paragraph","position":{"start":{"line":199,"column":1},"end":{"line":199,"column":1}},"children":[{"type":"text","value":"Lazy-loading is essential when working with large data collections, why?","position":{"start":{"line":199,"column":1},"end":{"line":199,"column":1}},"key":"rs90lERJ7Z"}],"key":"KM8NLZmZAZ"},{"type":"code","lang":"","value":"[(X)] Lazy-loading improves performance by loading data only when needed, reducing memory usage and speeding up application response times.\n[( )] Lazy-loading automatically compresses all data in large collections, leading to faster data retrieval.\n[( )] Lazy-loading duplicates data across multiple processes, ensuring data availability at all times.\n[(X)] Lazy-loading allows to process data which is larger than memory with appropriate chunking strategies.","position":{"start":{"line":201,"column":1},"end":{"line":204,"column":1}},"key":"cvxI1PLo5B"},{"type":"paragraph","position":{"start":{"line":206,"column":1},"end":{"line":206,"column":1}},"children":[{"type":"text","value":"Which of the following is correct when considering time-based chunking?","position":{"start":{"line":206,"column":1},"end":{"line":206,"column":1}},"key":"zgiEE7vfyI"}],"key":"yZtmTevIL3"},{"type":"code","lang":"","value":"[( )] It divides data into fixed-size cubes or boxes for balanced processing.\n[(X)] It organizes data based on temporal dimensions such as days, months, or years.\n[(X)] It is particularly useful for analyzing trends and patterns over time.","position":{"start":{"line":208,"column":1},"end":{"line":210,"column":1}},"key":"Dm02vvwGiG"},{"type":"paragraph","position":{"start":{"line":212,"column":1},"end":{"line":212,"column":1}},"children":[{"type":"text","value":"Consider a cloud provider, that should decide if compressing the data on its storage would let it spare money.","position":{"start":{"line":212,"column":1},"end":{"line":212,"column":1}},"key":"SYFbNqOVUu"}],"key":"a0L23uAxiC"},{"type":"paragraph","position":{"start":{"line":214,"column":1},"end":{"line":214,"column":1}},"children":[{"type":"text","value":"If the compression process of a COG takes 0.05 CPU hour every 1 GB of data, the total amount of COGs on the storage takes 1200 TB and one CPU hour costs 0.05€ for the first 10000 CPU hour and then 0.03€ for the rest, how much would the compression process cost?","position":{"start":{"line":214,"column":1},"end":{"line":214,"column":1}},"key":"unVQcf3ASs"}],"key":"WpF8OpBNM8"},{"type":"code","lang":"","value":"[( )] 3000€\n[( )] 1200€\n[(X)] 2000€\n[( )] 2043€","position":{"start":{"line":216,"column":1},"end":{"line":219,"column":1}},"key":"zQkwVSKmig"},{"type":"paragraph","position":{"start":{"line":221,"column":1},"end":{"line":221,"column":1}},"children":[{"type":"text","value":"Solution:","position":{"start":{"line":221,"column":1},"end":{"line":221,"column":1}},"key":"D6cs1Oq29z"}],"key":"qnMoqo4wMF"},{"type":"list","ordered":false,"spread":false,"position":{"start":{"line":222,"column":1},"end":{"line":228,"column":1}},"children":[{"type":"listItem","spread":true,"position":{"start":{"line":222,"column":1},"end":{"line":222,"column":1}},"children":[{"type":"paragraph","children":[{"type":"text","value":"1 TB = 1000 GB following the international standard, see ","position":{"start":{"line":222,"column":1},"end":{"line":222,"column":1}},"key":"Itijqhcc8o"},{"type":"link","url":"https://en.wikipedia.org/wiki/Gigabyte","position":{"start":{"line":222,"column":1},"end":{"line":222,"column":1}},"children":[{"type":"text","value":"Gigabyte","key":"gzCNC8f2nw"}],"urlSource":"https://en.wikipedia.org/wiki/Gigabyte","data":{"page":"Gigabyte","wiki":"https://en.wikipedia.org/","lang":"en"},"internal":false,"protocol":"wiki","key":"NMM7N7wSwF"},{"type":"text","value":".","position":{"start":{"line":222,"column":1},"end":{"line":222,"column":1}},"key":"CjObZuadfz"}],"key":"Im3YnFWjIa"}],"key":"d3KfWfpdG3"},{"type":"listItem","spread":true,"position":{"start":{"line":223,"column":1},"end":{"line":223,"column":1}},"children":[{"type":"paragraph","children":[{"type":"text","value":"The amount of data on the storage is 1200 TB * 1000 GB/TB = 1200000 GB","position":{"start":{"line":223,"column":1},"end":{"line":223,"column":1}},"key":"w4cjg2uWLp"}],"key":"BuWHev2Iun"}],"key":"dx9hu3gGKP"},{"type":"listItem","spread":true,"position":{"start":{"line":224,"column":1},"end":{"line":224,"column":1}},"children":[{"type":"paragraph","children":[{"type":"text","value":"If to compress 1 GB of data takes 0.05 CPU hour, to compress 1200000 GB it will take: 1200000 GB * 0.05 CPU hour / GB = 60000 CPU hour","position":{"start":{"line":224,"column":1},"end":{"line":224,"column":1}},"key":"j4K8pI0TKI"}],"key":"TOwsE7VejY"}],"key":"b2kF7OufUp"},{"type":"listItem","spread":true,"position":{"start":{"line":225,"column":1},"end":{"line":225,"column":1}},"children":[{"type":"paragraph","children":[{"type":"text","value":"The first 10000 CPU hour cost 10000 CPU hour * 0.05 €/CPU hour = 500€","position":{"start":{"line":225,"column":1},"end":{"line":225,"column":1}},"key":"SRBxeFMedK"}],"key":"cRxnrEraoz"}],"key":"SRrLgtrJYJ"},{"type":"listItem","spread":true,"position":{"start":{"line":226,"column":1},"end":{"line":226,"column":1}},"children":[{"type":"paragraph","children":[{"type":"text","value":"The rest is 50000 CPU hour and it will cost 50000 CPU hour * 0.03 €/CPU hour = 1500 €","position":{"start":{"line":226,"column":1},"end":{"line":226,"column":1}},"key":"cDSUD72NYa"}],"key":"jJFfeinJz6"}],"key":"RktfZlFkEy"},{"type":"listItem","spread":true,"position":{"start":{"line":227,"column":1},"end":{"line":228,"column":1}},"children":[{"type":"paragraph","children":[{"type":"text","value":"The total is 500 € + 1500 € = 2000 €","position":{"start":{"line":227,"column":1},"end":{"line":227,"column":1}},"key":"lxuhEK6JP2"}],"key":"NjFFoCgApW"}],"key":"DIIIzfaSVz"}],"key":"G61ZKjqJsq"},{"type":"paragraph","position":{"start":{"line":229,"column":1},"end":{"line":229,"column":1}},"children":[{"type":"text","value":"In the same scenario, now we also consider the storage maintanance cost. If each TB of storage has a maintenance cost of 0.5 € every month, how much time would it take before the compression would let the cloud provider spare money? Consider a compression rate of 70%.","position":{"start":{"line":229,"column":1},"end":{"line":229,"column":1}},"key":"PgpJo80p4J"}],"key":"j62k5fpRM6"},{"type":"code","lang":"","value":"[( )] ~ 9 months\n[( )] ~ 10 months\n[(X)] ~ 11 months\n[( )] ~ 12 months","position":{"start":{"line":231,"column":1},"end":{"line":234,"column":1}},"key":"LIC6jmlex1"},{"type":"paragraph","position":{"start":{"line":236,"column":1},"end":{"line":236,"column":1}},"children":[{"type":"text","value":"Solution:","position":{"start":{"line":236,"column":1},"end":{"line":236,"column":1}},"key":"gFRBfvBQ3t"}],"key":"vur6Zbu2a9"},{"type":"list","ordered":false,"spread":false,"position":{"start":{"line":237,"column":1},"end":{"line":242,"column":1}},"children":[{"type":"listItem","spread":true,"position":{"start":{"line":237,"column":1},"end":{"line":237,"column":1}},"children":[{"type":"paragraph","children":[{"type":"text","value":"Without compression, every month the storage would cost: 1200 TB * 0.5 €/TB = 600 €","position":{"start":{"line":237,"column":1},"end":{"line":237,"column":1}},"key":"i7V1SLxqwm"}],"key":"x9QG2XM9SN"}],"key":"Dt23Ku0UNA"},{"type":"listItem","spread":true,"position":{"start":{"line":238,"column":1},"end":{"line":238,"column":1}},"children":[{"type":"paragraph","children":[{"type":"text","value":"With a compression rate of 70%, the data would use 1200 TB * 0.7 = 840 TB of disk space","position":{"start":{"line":238,"column":1},"end":{"line":238,"column":1}},"key":"MN9WWStldl"}],"key":"A2HvFq5paE"}],"key":"JWPpx7UKzh"},{"type":"listItem","spread":true,"position":{"start":{"line":239,"column":1},"end":{"line":239,"column":1}},"children":[{"type":"paragraph","children":[{"type":"text","value":"With compression, every month the storage would cost: 840 TB * 0.5 €/TB = 420 €","position":{"start":{"line":239,"column":1},"end":{"line":239,"column":1}},"key":"sdvJpvm2gr"}],"key":"JMIMvyCTsf"}],"key":"Id7zuMZx3x"},{"type":"listItem","spread":true,"position":{"start":{"line":240,"column":1},"end":{"line":240,"column":1}},"children":[{"type":"paragraph","children":[{"type":"text","value":"With compression, each month it’s possible to spare 180 €.","position":{"start":{"line":240,"column":1},"end":{"line":240,"column":1}},"key":"aqjg9Iwafy"}],"key":"Wbd5pAWubw"}],"key":"adnxdNsY1J"},{"type":"listItem","spread":true,"position":{"start":{"line":241,"column":1},"end":{"line":242,"column":1}},"children":[{"type":"paragraph","children":[{"type":"text","value":"Since the compression process costs 2000 €, and each month costs 180 € less with it, it would take 2000 € / 180 €/month ~= 11 months to start to spare money.","position":{"start":{"line":241,"column":1},"end":{"line":241,"column":1}},"key":"sTrPYcwVtr"}],"key":"P3ezf2sMNE"}],"key":"JNExGN2pgL"}],"key":"H4cxCbuBSp"},{"type":"paragraph","position":{"start":{"line":243,"column":1},"end":{"line":243,"column":1}},"children":[{"type":"text","value":"What does ","position":{"start":{"line":243,"column":1},"end":{"line":243,"column":1}},"key":"ReDBZgBt3r"},{"type":"inlineCode","value":"CodeCarbon","position":{"start":{"line":243,"column":1},"end":{"line":243,"column":1}},"key":"fZyK7KWnpP"},{"type":"text","value":" measure in Python code? ","position":{"start":{"line":243,"column":1},"end":{"line":243,"column":1}},"key":"IvNfhbeFMh"},{"type":"emphasis","position":{"start":{"line":243,"column":1},"end":{"line":243,"column":1}},"children":[{"type":"text","value":"Answer in exercise: 24_energy_consumption.ipynb","position":{"start":{"line":243,"column":1},"end":{"line":243,"column":1}},"key":"E4yJlQfjzo"}],"key":"I5T8RWjbRC"}],"key":"kSmFU4nYA3"},{"type":"code","lang":"","value":"[( )] Code execution speed\n[(X)] Energy consumption of code execution\n[( )] Memory usage of variables\n[( )] The number of lines in the code","position":{"start":{"line":245,"column":1},"end":{"line":248,"column":1}},"key":"cJ17vU8DCJ"},{"type":"paragraph","position":{"start":{"line":250,"column":1},"end":{"line":250,"column":1}},"children":[{"type":"text","value":"Approximately how many meters of driving a Mars rover would consume the same amount of energy as our sample NDVI workflow? ","position":{"start":{"line":250,"column":1},"end":{"line":250,"column":1}},"key":"qDRNqYJNov"},{"type":"emphasis","position":{"start":{"line":250,"column":1},"end":{"line":250,"column":1}},"children":[{"type":"text","value":"Answer in exercise: 24_energy_consumption.ipynb","position":{"start":{"line":250,"column":1},"end":{"line":250,"column":1}},"key":"aZ0QlWPhbn"}],"key":"gDeMkz40X1"}],"key":"F8q5Gio3rS"},{"type":"code","lang":"","value":"[(X)] 0-2 meter\n[( )] 2-4 meters\n[( )] 4-6 meters\n[( )] 6-8 meters","position":{"start":{"line":252,"column":1},"end":{"line":255,"column":1}},"key":"eqyGfvnpL2"}],"key":"obLFPdQSFI"}],"key":"G1b6nN2wFq"},"references":{"cite":{"order":["https://doi.org/10.5281/zenodo.11171501"],"data":{"https://doi.org/10.5281/zenodo.11171501":{"label":"https://doi.org/10.5281/zenodo.11171501","enumerator":"1","doi":"10.5281/ZENODO.11171501","html":"Benoit Courty, Victor Schmidt, Goyal-Kamal, MarionCoutarel, Boris Feld, Jérémy Lecourt, LiamConnell, SabAmine, inimaz, supatomic, Mathilde Léval, Luis Blanche, Alexis Cruveiller, ouminasara, Franklin Zhao, Aditya Joshi, Alexis Bogroff, Amine Saboni, Hugues de Lavoreille, … MinervaBooks. (2024). <i>mlco2/codecarbon: v2.4.1</i>. Zenodo. <a target=\"_blank\" rel=\"noreferrer\" href=\"https://doi.org/10.5281/ZENODO.11171501\">10.5281/ZENODO.11171501</a>","url":"https://doi.org/10.5281/ZENODO.11171501"}}}},"footer":{"navigation":{"prev":{"title":"2.3 Data Access and Basic Processing Pangeo Apply","url":"/lectures/data-access/exercises/pangeo/pangeo-data-access-apply","group":"Data access with pangeo"},"next":{"title":"2.4 Data Chunking with Pangeo","url":"/lectures/formats-and-performance/exercises/chunking","group":"Data formats for achieving scalability"}}},"domain":"http://localhost:3000"}